[{"line_id": 1, "speaker": "PRIAM", "text": "After\n               \n              so\n               \n              many\n               \n              hours\n              ,\n               \n              lives\n              ,\n               \n              speeches\n               \n              spent\n              ,"}, {"line_id": 2, "speaker": "PRIAM", "text": "Thus\n               \n              once\n               \n              again\n               \n              says\n               \n              Nestor\n               \n              from\n               \n              the\n               \n              Greeks\n              :"}, {"line_id": 3, "speaker": "PRIAM", "text": "“\n              Deliver\n               \n              Helen\n              ,\n               \n              and\n               \n              all\n               \n              damage\n               \n              else\n              —"}, {"line_id": 4, "speaker": "PRIAM", "text": "As\n               \n              honor\n              ,\n               \n              loss\n               \n              of\n               \n              time\n              ,\n               \n              travel\n              ,\n               \n              expense\n              ,"}, {"line_id": 5, "speaker": "PRIAM", "text": "Wounds\n              ,\n               \n              friends\n              ,\n               \n              and\n               \n              what\n               \n              else\n               \n              dear\n               \n              that\n               \n              is\n               \n              consumed"}, {"line_id": 6, "speaker": "PRIAM", "text": "In\n               \n              hot\n               \n              digestion\n               \n              of\n               \n              this\n               \n              cormorant\n               \n              war\n              —"}, {"line_id": 7, "speaker": "PRIAM", "text": "Shall\n               \n              be\n               \n              struck\n               \n              off\n              .\n              ”\n              —\n              Hector\n              ,\n               \n              what\n               \n              say\n               \n              you\n               \n              to\n               \n              ’t\n              ?"}, {"line_id": 8, "speaker": "HECTOR", "text": "Though\n               \n              no\n               \n              man\n               \n              lesser\n               \n              fears\n               \n              the\n               \n              Greeks\n               \n              than\n               \n              I"}, {"line_id": 9, "speaker": "HECTOR", "text": "As\n               \n              far\n               \n              as\n               \n              toucheth\n               \n              my\n               \n              particular\n              ,"}, {"line_id": 10, "speaker": "HECTOR", "text": "Yet\n              ,\n               \n              dread\n               \n              Priam\n              ,"}, {"line_id": 11, "speaker": "HECTOR", "text": "There\n               \n              is\n               \n              no\n               \n              lady\n               \n              of\n               \n              more\n               \n              softer\n               \n              bowels\n              ,"}, {"line_id": 12, "speaker": "HECTOR", "text": "More\n               \n              spongy\n               \n              to\n               \n              suck\n               \n              in\n               \n              the\n               \n              sense\n               \n              of\n               \n              fear\n              ,"}, {"line_id": 13, "speaker": "HECTOR", "text": "More\n               \n              ready\n               \n              to\n               \n              cry\n               \n              out\n               \n              “\n              Who\n               \n              knows\n               \n              what\n               \n              follows\n              ?\n              ”"}, {"line_id": 14, "speaker": "HECTOR", "text": "Than\n               \n              Hector\n               \n              is\n              .\n               \n              The\n               \n              wound\n               \n              of\n               \n              peace\n               \n              is\n               \n              surety\n              ,"}, {"line_id": 15, "speaker": "HECTOR", "text": "Surety\n               \n              secure\n              ;\n               \n              but\n               \n              modest\n               \n              doubt\n               \n              is\n               \n              called"}, {"line_id": 16, "speaker": "HECTOR", "text": "The\n               \n              beacon\n               \n              of\n               \n              the\n               \n              wise\n              ,\n               \n              the\n               \n              tent\n               \n              that\n               \n              searches"}, {"line_id": 17, "speaker": "HECTOR", "text": "To\n               \n              th’\n               \n              bottom\n               \n              of\n               \n              the\n               \n              worst\n              .\n               \n              Let\n               \n              Helen\n               \n              go\n              ."}, {"line_id": 18, "speaker": "HECTOR", "text": "Since\n               \n              the\n               \n              first\n               \n              sword\n               \n              was\n               \n              drawn\n               \n              about\n               \n              this\n               \n              question\n              ,"}, {"line_id": 19, "speaker": "HECTOR", "text": "Every\n               \n              tithe\n               \n              soul\n              ,\n               \n              ’mongst\n               \n              many\n               \n              thousand\n               \n              dismes\n              ,"}, {"line_id": 20, "speaker": "HECTOR", "text": "Hath\n               \n              been\n               \n              as\n               \n              dear\n               \n              as\n               \n              Helen\n              ;\n               \n              I\n               \n              mean\n              ,\n               \n              of\n               \n              ours\n              ."}, {"line_id": 21, "speaker": "HECTOR", "text": "If\n               \n              we\n               \n              have\n               \n              lost\n               \n              so\n               \n              many\n               \n              tenths\n               \n              of\n               \n              ours"}, {"line_id": 22, "speaker": "HECTOR", "text": "To\n               \n              guard\n               \n              a\n               \n              thing\n               \n              not\n               \n              ours\n              —\n              nor\n               \n              worth\n               \n              to\n               \n              us\n              ,"}, {"line_id": 23, "speaker": "HECTOR", "text": "Had\n               \n              it\n               \n              our\n               \n              name\n              ,\n               \n              the\n               \n              value\n               \n              of\n               \n              one\n               \n              ten\n              —"}, {"line_id": 24, "speaker": "HECTOR", "text": "What\n               \n              merit’s\n               \n              in\n               \n              that\n               \n              reason\n               \n              which\n               \n              denies"}, {"line_id": 25, "speaker": "HECTOR", "text": "The\n               \n              yielding\n               \n              of\n               \n              her\n               \n              up\n              ?"}, {"line_id": 26, "speaker": "TROILUS", "text": "Fie\n              ,\n               \n              fie\n              ,\n               \n              my\n               \n              brother\n              ,"}, {"line_id": 27, "speaker": "TROILUS", "text": "Weigh\n               \n              you\n               \n              the\n               \n              worth\n               \n              and\n               \n              honor\n               \n              of\n               \n              a\n               \n              king"}, {"line_id": 28, "speaker": "TROILUS", "text": "So\n               \n              great\n               \n              as\n               \n              our\n               \n              dread\n               \n              father’s\n               \n              in\n               \n              a\n               \n              scale"}, {"line_id": 29, "speaker": "TROILUS", "text": "Of\n               \n              common\n               \n              ounces\n              ?\n               \n              Will\n               \n              you\n               \n              with\n               \n              counters\n               \n              sum"}, {"line_id": 30, "speaker": "TROILUS", "text": "The\n               \n              past-proportion\n               \n              of\n               \n              his\n               \n              infinite\n              ,"}, {"line_id": 31, "speaker": "TROILUS", "text": "And\n               \n              buckle\n               \n              in\n               \n              a\n               \n              waist\n               \n              most\n               \n              fathomless"}, {"line_id": 32, "speaker": "TROILUS", "text": "With\n               \n              spans\n               \n              and\n               \n              inches\n               \n              so\n               \n              diminutive"}, {"line_id": 33, "speaker": "TROILUS", "text": "As\n               \n              fears\n               \n              and\n               \n              reasons\n              ?\n               \n              Fie\n              ,\n               \n              for\n               \n              godly\n               \n              shame\n              !"}, {"line_id": 34, "speaker": "HELENUS", "text": "No\n               \n              marvel\n               \n              though\n               \n              you\n               \n              bite\n               \n              so\n               \n              sharp\n               \n              at\n               \n              reasons\n              ,"}, {"line_id": 35, "speaker": "HELENUS", "text": "You\n               \n              are\n               \n              so\n               \n              empty\n               \n              of\n               \n              them\n              .\n               \n              Should\n               \n              not\n               \n              our\n               \n              father"}, {"line_id": 36, "speaker": "HELENUS", "text": "Bear\n               \n              the\n               \n              great\n               \n              sway\n               \n              of\n               \n              his\n               \n              affairs\n               \n              with\n               \n              reason\n              ,"}, {"line_id": 37, "speaker": "HELENUS", "text": "Because\n               \n              your\n               \n              speech\n               \n              hath\n               \n              none\n               \n              that\n               \n              tell\n               \n              him\n               \n              so\n              ?"}, {"line_id": 38, "speaker": "TROILUS", "text": "You\n               \n              are\n               \n              for\n               \n              dreams\n               \n              and\n               \n              slumbers\n              ,\n               \n              brother\n               \n              priest\n              ."}, {"line_id": 39, "speaker": "TROILUS", "text": "You\n               \n              fur\n               \n              your\n               \n              gloves\n               \n              with\n               \n              reason\n              .\n               \n              Here\n               \n              are\n               \n              your\n               \n              reasons\n              :"}, {"line_id": 40, "speaker": "TROILUS", "text": "You\n               \n              know\n               \n              an\n               \n              enemy\n               \n              intends\n               \n              you\n               \n              harm\n              ;"}, {"line_id": 41, "speaker": "TROILUS", "text": "You\n               \n              know\n               \n              a\n               \n              sword\n               \n              employed\n               \n              is\n               \n              perilous\n              ,"}, {"line_id": 42, "speaker": "TROILUS", "text": "And\n               \n              reason\n               \n              flies\n               \n              the\n               \n              object\n               \n              of\n               \n              all\n               \n              harm\n              ."}, {"line_id": 43, "speaker": "TROILUS", "text": "Who\n               \n              marvels\n              ,\n               \n              then\n              ,\n               \n              when\n               \n              Helenus\n               \n              beholds"}, {"line_id": 44, "speaker": "TROILUS", "text": "A\n               \n              Grecian\n               \n              and\n               \n              his\n               \n              sword\n              ,\n               \n              if\n               \n              he\n               \n              do\n               \n              set"}, {"line_id": 45, "speaker": "TROILUS", "text": "The\n               \n              very\n               \n              wings\n               \n              of\n               \n              reason\n               \n              to\n               \n              his\n               \n              heels"}, {"line_id": 46, "speaker": "TROILUS", "text": "And\n               \n              fly\n               \n              like\n               \n              chidden\n               \n              Mercury\n               \n              from\n               \n              Jove"}, {"line_id": 47, "speaker": "TROILUS", "text": "Or\n               \n              like\n               \n              a\n               \n              star\n               \n              disorbed\n              ?\n               \n              Nay\n              ,\n               \n              if\n               \n              we\n               \n              talk\n               \n              of\n               \n              reason\n              ,"}, {"line_id": 48, "speaker": "TROILUS", "text": "Let’s\n               \n              shut\n               \n              our\n               \n              gates\n               \n              and\n               \n              sleep\n              .\n               \n              Manhood\n               \n              and\n               \n              honor"}, {"line_id": 49, "speaker": "TROILUS", "text": "Should\n               \n              have\n               \n              hare\n               \n              hearts\n              ,\n               \n              would\n               \n              they\n               \n              but\n               \n              fat\n               \n              their\n               \n              thoughts"}, {"line_id": 50, "speaker": "TROILUS", "text": "With\n               \n              this\n               \n              crammed\n               \n              reason\n              .\n               \n              Reason\n               \n              and\n               \n              respect"}, {"line_id": 51, "speaker": "TROILUS", "text": "Make\n               \n              livers\n               \n              pale\n               \n              and\n               \n              lustihood\n               \n              deject\n              ."}, {"line_id": 52, "speaker": "HECTOR", "text": "Brother\n              ,\n               \n              she\n               \n              is\n               \n              not\n               \n              worth\n               \n              what\n               \n              she\n               \n              doth\n               \n              cost"}, {"line_id": 53, "speaker": "HECTOR", "text": "The\n               \n              keeping\n              ."}, {"line_id": 54, "speaker": "TROILUS", "text": "What’s\n               \n              aught\n               \n              but\n               \n              as\n               \n              ’tis\n               \n              valued\n              ?"}, {"line_id": 55, "speaker": "HECTOR", "text": "But\n               \n              value\n               \n              dwells\n               \n              not\n               \n              in\n               \n              particular\n               \n              will\n              ;"}, {"line_id": 56, "speaker": "HECTOR", "text": "It\n               \n              holds\n               \n              his\n               \n              estimate\n               \n              and\n               \n              dignity"}, {"line_id": 57, "speaker": "HECTOR", "text": "As\n               \n              well\n               \n              wherein\n               \n              ’tis\n               \n              precious\n               \n              of\n               \n              itself"}, {"line_id": 58, "speaker": "HECTOR", "text": "As\n               \n              in\n               \n              the\n               \n              prizer\n              .\n               \n              ’Tis\n               \n              mad\n               \n              idolatry"}, {"line_id": 59, "speaker": "HECTOR", "text": "To\n               \n              make\n               \n              the\n               \n              service\n               \n              greater\n               \n              than\n               \n              the\n               \n              god\n              ;"}, {"line_id": 60, "speaker": "HECTOR", "text": "And\n               \n              the\n               \n              will\n               \n              dotes\n               \n              that\n               \n              is\n               \n              attributive"}, {"line_id": 61, "speaker": "HECTOR", "text": "To\n               \n              what\n               \n              infectiously\n               \n              itself\n               \n              affects"}, {"line_id": 62, "speaker": "HECTOR", "text": "Without\n               \n              some\n               \n              image\n               \n              of\n               \n              th’\n               \n              affected\n               \n              merit\n              ."}, {"line_id": 63, "speaker": "TROILUS", "text": "I\n               \n              take\n               \n              today\n               \n              a\n               \n              wife\n              ,\n               \n              and\n               \n              my\n               \n              election"}, {"line_id": 64, "speaker": "TROILUS", "text": "Is\n               \n              led\n               \n              on\n               \n              in\n               \n              the\n               \n              conduct\n               \n              of\n               \n              my\n               \n              will\n              —"}, {"line_id": 65, "speaker": "TROILUS", "text": "My\n               \n              will\n               \n              enkindled\n               \n              by\n               \n              mine\n               \n              eyes\n               \n              and\n               \n              ears\n              ,"}, {"line_id": 66, "speaker": "TROILUS", "text": "Two\n               \n              traded\n               \n              pilots\n               \n              ’twixt\n               \n              the\n               \n              dangerous\n               \n              shores"}, {"line_id": 67, "speaker": "TROILUS", "text": "Of\n               \n              will\n               \n              and\n               \n              judgment\n              .\n               \n              How\n               \n              may\n               \n              I\n               \n              avoid\n              ,"}, {"line_id": 68, "speaker": "TROILUS", "text": "Although\n               \n              my\n               \n              will\n               \n              distaste\n               \n              what\n               \n              it\n               \n              elected\n              ,"}, {"line_id": 69, "speaker": "TROILUS", "text": "The\n               \n              wife\n               \n              I\n               \n              choose\n              ?\n               \n              There\n               \n              can\n               \n              be\n               \n              no\n               \n              evasion"}, {"line_id": 70, "speaker": "TROILUS", "text": "To\n               \n              blench\n               \n              from\n               \n              this\n               \n              and\n               \n              to\n               \n              stand\n               \n              firm\n               \n              by\n               \n              honor\n              ."}, {"line_id": 71, "speaker": "TROILUS", "text": "We\n               \n              turn\n               \n              not\n               \n              back\n               \n              the\n               \n              silks\n               \n              upon\n               \n              the\n               \n              merchant"}, {"line_id": 72, "speaker": "TROILUS", "text": "When\n               \n              we\n               \n              have\n               \n              soiled\n               \n              them\n              ,\n               \n              nor\n               \n              the\n               \n              remainder\n               \n              viands"}, {"line_id": 73, "speaker": "TROILUS", "text": "We\n               \n              do\n               \n              not\n               \n              throw\n               \n              in\n               \n              unrespective\n               \n              sieve"}, {"line_id": 74, "speaker": "TROILUS", "text": "Because\n               \n              we\n               \n              now\n               \n              are\n               \n              full\n              .\n               \n              It\n               \n              was\n               \n              thought\n               \n              meet"}, {"line_id": 75, "speaker": "TROILUS", "text": "Paris\n               \n              should\n               \n              do\n               \n              some\n               \n              vengeance\n               \n              on\n               \n              the\n               \n              Greeks\n              ."}, {"line_id": 76, "speaker": "TROILUS", "text": "Your\n               \n              breath\n               \n              with\n               \n              full\n               \n              consent\n               \n              bellied\n               \n              his\n               \n              sails\n              ;"}, {"line_id": 77, "speaker": "TROILUS", "text": "The\n               \n              seas\n               \n              and\n               \n              winds\n              ,\n               \n              old\n               \n              wranglers\n              ,\n               \n              took\n               \n              a\n               \n              truce"}, {"line_id": 78, "speaker": "TROILUS", "text": "And\n               \n              did\n               \n              him\n               \n              service\n              .\n               \n              He\n               \n              touched\n               \n              the\n               \n              ports\n               \n              desired\n              ,"}, {"line_id": 79, "speaker": "TROILUS", "text": "And\n               \n              for\n               \n              an\n               \n              old\n               \n              aunt\n               \n              whom\n               \n              the\n               \n              Greeks\n               \n              held\n               \n              captive\n              ,"}, {"line_id": 80, "speaker": "TROILUS", "text": "He\n               \n              brought\n               \n              a\n               \n              Grecian\n               \n              queen\n              ,\n               \n              whose\n               \n              youth\n               \n              and\n               \n              freshness"}, {"line_id": 81, "speaker": "TROILUS", "text": "Wrinkles\n               \n              Apollo’s\n               \n              and\n               \n              makes\n               \n              pale\n               \n              the\n               \n              morning\n              ."}, {"line_id": 82, "speaker": "TROILUS", "text": "Why\n               \n              keep\n               \n              we\n               \n              her\n              ?\n               \n              The\n               \n              Grecians\n               \n              keep\n               \n              our\n               \n              aunt\n              ."}, {"line_id": 83, "speaker": "TROILUS", "text": "Is\n               \n              she\n               \n              worth\n               \n              keeping\n              ?\n               \n              Why\n              ,\n               \n              she\n               \n              is\n               \n              a\n               \n              pearl"}, {"line_id": 84, "speaker": "TROILUS", "text": "Whose\n               \n              price\n               \n              hath\n               \n              launched\n               \n              above\n               \n              a\n               \n              thousand\n               \n              ships"}, {"line_id": 85, "speaker": "TROILUS", "text": "And\n               \n              turned\n               \n              crowned\n               \n              kings\n               \n              to\n               \n              merchants\n              ."}, {"line_id": 86, "speaker": "TROILUS", "text": "If\n               \n              you’ll\n               \n              avouch\n               \n              ’twas\n               \n              wisdom\n               \n              Paris\n               \n              went\n              —"}, {"line_id": 87, "speaker": "TROILUS", "text": "As\n               \n              you\n               \n              must\n               \n              needs\n              ,\n               \n              for\n               \n              you\n               \n              all\n               \n              cried\n               \n              “\n              Go\n              ,\n               \n              go\n              ”\n              —"}, {"line_id": 88, "speaker": "TROILUS", "text": "If\n               \n              you’ll\n               \n              confess\n               \n              he\n               \n              brought\n               \n              home\n               \n              worthy\n               \n              prize\n              —"}, {"line_id": 89, "speaker": "TROILUS", "text": "As\n               \n              you\n               \n              must\n               \n              needs\n              ,\n               \n              for\n               \n              you\n               \n              all\n               \n              clapped\n               \n              your\n               \n              hands"}, {"line_id": 90, "speaker": "TROILUS", "text": "And\n               \n              cried\n               \n              “\n              Inestimable\n              ”\n              —\n              why\n               \n              do\n               \n              you\n               \n              now"}, {"line_id": 91, "speaker": "TROILUS", "text": "The\n               \n              issue\n               \n              of\n               \n              your\n               \n              proper\n               \n              wisdoms\n               \n              rate"}, {"line_id": 92, "speaker": "TROILUS", "text": "And\n               \n              do\n               \n              a\n               \n              deed\n               \n              that\n               \n              never\n               \n              Fortune\n               \n              did\n              ,"}, {"line_id": 93, "speaker": "TROILUS", "text": "Beggar\n               \n              the\n               \n              estimation\n               \n              which\n               \n              you\n               \n              prized"}, {"line_id": 94, "speaker": "TROILUS", "text": "Richer\n               \n              than\n               \n              sea\n               \n              and\n               \n              land\n              ?\n               \n              O\n              ,\n               \n              theft\n               \n              most\n               \n              base\n              ,"}, {"line_id": 95, "speaker": "TROILUS", "text": "That\n               \n              we\n               \n              have\n               \n              stol’n\n               \n              what\n               \n              we\n               \n              do\n               \n              fear\n               \n              to\n               \n              keep\n              !"}, {"line_id": 96, "speaker": "TROILUS", "text": "But\n               \n              thieves\n               \n              unworthy\n               \n              of\n               \n              a\n               \n              thing\n               \n              so\n               \n              stol’n\n              ,"}, {"line_id": 97, "speaker": "TROILUS", "text": "That\n               \n              in\n               \n              their\n               \n              country\n               \n              did\n               \n              them\n               \n              that\n               \n              disgrace"}, {"line_id": 98, "speaker": "TROILUS", "text": "We\n               \n              fear\n               \n              to\n               \n              warrant\n               \n              in\n               \n              our\n               \n              native\n               \n              place\n              ."}, {"line_id": 99, "speaker": "CASSANDRA", "text": "Cry\n              ,\n               \n              Trojans\n              ,\n               \n              cry\n              !"}, {"line_id": 100, "speaker": "PRIAM", "text": "What\n               \n              noise\n              ?\n               \n              What\n               \n              shriek\n               \n              is\n               \n              this\n              ?"}, {"line_id": 101, "speaker": "TROILUS", "text": "’Tis\n               \n              our\n               \n              mad\n               \n              sister\n              .\n               \n              I\n               \n              do\n               \n              know\n               \n              her\n               \n              voice\n              ."}, {"line_id": 102, "speaker": "CASSANDRA", "text": "Cry\n              ,\n               \n              Trojans\n              !"}, {"line_id": 103, "speaker": "HECTOR", "text": "It\n               \n              is\n               \n              Cassandra\n              ."}, {"line_id": 104, "speaker": "CASSANDRA", "text": "Cry\n              ,\n               \n              Trojans\n              ,\n               \n              cry\n              !\n               \n              Lend\n               \n              me\n               \n              ten\n               \n              thousand\n               \n              eyes\n              ,"}, {"line_id": 105, "speaker": "CASSANDRA", "text": "And\n               \n              I\n               \n              will\n               \n              fill\n               \n              them\n               \n              with\n               \n              prophetic\n               \n              tears\n              ."}, {"line_id": 106, "speaker": "HECTOR", "text": "Peace\n              ,\n               \n              sister\n              ,\n               \n              peace\n              !"}, {"line_id": 107, "speaker": "CASSANDRA", "text": "Virgins\n               \n              and\n               \n              boys\n              ,\n               \n              mid-age\n               \n              and\n               \n              wrinkled\n               \n              elders\n              ,"}, {"line_id": 108, "speaker": "CASSANDRA", "text": "Soft\n               \n              infancy\n              ,\n               \n              that\n               \n              nothing\n               \n              canst\n               \n              but\n               \n              cry\n              ,"}, {"line_id": 109, "speaker": "CASSANDRA", "text": "Add\n               \n              to\n               \n              my\n               \n              clamors\n              .\n               \n              Let\n               \n              us\n               \n              pay\n               \n              betimes"}, {"line_id": 110, "speaker": "CASSANDRA", "text": "A\n               \n              moiety\n               \n              of\n               \n              that\n               \n              mass\n               \n              of\n               \n              moan\n               \n              to\n               \n              come\n              ."}, {"line_id": 111, "speaker": "CASSANDRA", "text": "Cry\n              ,\n               \n              Trojans\n              ,\n               \n              cry\n              !\n               \n              Practice\n               \n              your\n               \n              eyes\n               \n              with\n               \n              tears\n              ."}, {"line_id": 112, "speaker": "CASSANDRA", "text": "Troy\n               \n              must\n               \n              not\n               \n              be\n              ,\n               \n              nor\n               \n              goodly\n               \n              Ilium\n               \n              stand\n              ."}, {"line_id": 113, "speaker": "CASSANDRA", "text": "Our\n               \n              firebrand\n               \n              brother\n               \n              Paris\n               \n              burns\n               \n              us\n               \n              all\n              ."}, {"line_id": 114, "speaker": "CASSANDRA", "text": "Cry\n              ,\n               \n              Trojans\n              ,\n               \n              cry\n              !\n               \n              A\n               \n              Helen\n               \n              and\n               \n              a\n               \n              woe\n              !"}, {"line_id": 115, "speaker": "CASSANDRA", "text": "Cry\n              ,\n               \n              cry\n              !\n               \n              Troy\n               \n              burns\n              ,\n               \n              or\n               \n              else\n               \n              let\n               \n              Helen\n               \n              go\n              ."}, {"line_id": 116, "speaker": "HECTOR", "text": "Now\n              ,\n               \n              youthful\n               \n              Troilus\n              ,\n               \n              do\n               \n              not\n               \n              these\n               \n              high\n               \n              strains"}, {"line_id": 117, "speaker": "HECTOR", "text": "Of\n               \n              divination\n               \n              in\n               \n              our\n               \n              sister\n               \n              work"}, {"line_id": 118, "speaker": "HECTOR", "text": "Some\n               \n              touches\n               \n              of\n               \n              remorse\n              ?\n               \n              Or\n               \n              is\n               \n              your\n               \n              blood"}, {"line_id": 119, "speaker": "HECTOR", "text": "So\n               \n              madly\n               \n              hot\n               \n              that\n               \n              no\n               \n              discourse\n               \n              of\n               \n              reason"}, {"line_id": 120, "speaker": "HECTOR", "text": "Nor\n               \n              fear\n               \n              of\n               \n              bad\n               \n              success\n               \n              in\n               \n              a\n               \n              bad\n               \n              cause"}, {"line_id": 121, "speaker": "HECTOR", "text": "Can\n               \n              qualify\n               \n              the\n               \n              same\n              ?"}, {"line_id": 122, "speaker": "TROILUS", "text": "Why\n              ,\n               \n              brother\n               \n              Hector\n              ,"}, {"line_id": 123, "speaker": "TROILUS", "text": "We\n               \n              may\n               \n              not\n               \n              think\n               \n              the\n               \n              justness\n               \n              of\n               \n              each\n               \n              act"}, {"line_id": 124, "speaker": "TROILUS", "text": "Such\n               \n              and\n               \n              no\n               \n              other\n               \n              than\n               \n              event\n               \n              doth\n               \n              form\n               \n              it\n              ,"}, {"line_id": 125, "speaker": "TROILUS", "text": "Nor\n               \n              once\n               \n              deject\n               \n              the\n               \n              courage\n               \n              of\n               \n              our\n               \n              minds"}, {"line_id": 126, "speaker": "TROILUS", "text": "Because\n               \n              Cassandra’s\n               \n              mad\n              .\n               \n              Her\n               \n              brainsick\n               \n              raptures"}, {"line_id": 127, "speaker": "TROILUS", "text": "Cannot\n               \n              distaste\n               \n              the\n               \n              goodness\n               \n              of\n               \n              a\n               \n              quarrel"}, {"line_id": 128, "speaker": "TROILUS", "text": "Which\n               \n              hath\n               \n              our\n               \n              several\n               \n              honors\n               \n              all\n               \n              engaged"}, {"line_id": 129, "speaker": "TROILUS", "text": "To\n               \n              make\n               \n              it\n               \n              gracious\n              .\n               \n              For\n               \n              my\n               \n              private\n               \n              part\n              ,"}, {"line_id": 130, "speaker": "TROILUS", "text": "I\n               \n              am\n               \n              no\n               \n              more\n               \n              touched\n               \n              than\n               \n              all\n               \n              Priam’s\n               \n              sons\n              ;"}, {"line_id": 131, "speaker": "TROILUS", "text": "And\n               \n              Jove\n               \n              forbid\n               \n              there\n               \n              should\n               \n              be\n               \n              done\n               \n              amongst\n               \n              us"}, {"line_id": 132, "speaker": "TROILUS", "text": "Such\n               \n              things\n               \n              as\n               \n              might\n               \n              offend\n               \n              the\n               \n              weakest\n               \n              spleen"}, {"line_id": 133, "speaker": "TROILUS", "text": "To\n               \n              fight\n               \n              for\n               \n              and\n               \n              maintain\n              !"}, {"line_id": 134, "speaker": "PARIS", "text": "Else\n               \n              might\n               \n              the\n               \n              world\n               \n              convince\n               \n              of\n               \n              levity"}, {"line_id": 135, "speaker": "PARIS", "text": "As\n               \n              well\n               \n              my\n               \n              undertakings\n               \n              as\n               \n              your\n               \n              counsels\n              ."}, {"line_id": 136, "speaker": "PARIS", "text": "But\n               \n              I\n               \n              attest\n               \n              the\n               \n              gods\n              ,\n               \n              your\n               \n              full\n               \n              consent"}, {"line_id": 137, "speaker": "PARIS", "text": "Gave\n               \n              wings\n               \n              to\n               \n              my\n               \n              propension\n               \n              and\n               \n              cut\n               \n              off"}, {"line_id": 138, "speaker": "PARIS", "text": "All\n               \n              fears\n               \n              attending\n               \n              on\n               \n              so\n               \n              dire\n               \n              a\n               \n              project\n              ."}, {"line_id": 139, "speaker": "PARIS", "text": "For\n               \n              what\n              ,\n               \n              alas\n              ,\n               \n              can\n               \n              these\n               \n              my\n               \n              single\n               \n              arms\n              ?"}, {"line_id": 140, "speaker": "PARIS", "text": "What\n               \n              propugnation\n               \n              is\n               \n              in\n               \n              one\n               \n              man’s\n               \n              valor"}, {"line_id": 141, "speaker": "PARIS", "text": "To\n               \n              stand\n               \n              the\n               \n              push\n               \n              and\n               \n              enmity\n               \n              of\n               \n              those"}, {"line_id": 142, "speaker": "PARIS", "text": "This\n               \n              quarrel\n               \n              would\n               \n              excite\n              ?\n               \n              Yet\n              ,\n               \n              I\n               \n              protest\n              ,"}, {"line_id": 143, "speaker": "PARIS", "text": "Were\n               \n              I\n               \n              alone\n               \n              to\n               \n              pass\n               \n              the\n               \n              difficulties"}, {"line_id": 144, "speaker": "PARIS", "text": "And\n               \n              had\n               \n              as\n               \n              ample\n               \n              power\n               \n              as\n               \n              I\n               \n              have\n               \n              will\n              ,"}, {"line_id": 145, "speaker": "PARIS", "text": "Paris\n               \n              should\n               \n              ne’er\n               \n              retract\n               \n              what\n               \n              he\n               \n              hath\n               \n              done"}, {"line_id": 146, "speaker": "PARIS", "text": "Nor\n               \n              faint\n               \n              in\n               \n              the\n               \n              pursuit\n              ."}, {"line_id": 147, "speaker": "PRIAM", "text": "Paris\n              ,\n               \n              you\n               \n              speak"}, {"line_id": 148, "speaker": "PRIAM", "text": "Like\n               \n              one\n               \n              besotted\n               \n              on\n               \n              your\n               \n              sweet\n               \n              delights\n              ."}, {"line_id": 149, "speaker": "PRIAM", "text": "You\n               \n              have\n               \n              the\n               \n              honey\n               \n              still\n              ,\n               \n              but\n               \n              these\n               \n              the\n               \n              gall\n              ."}, {"line_id": 150, "speaker": "PRIAM", "text": "So\n               \n              to\n               \n              be\n               \n              valiant\n               \n              is\n               \n              no\n               \n              praise\n               \n              at\n               \n              all\n              ."}, {"line_id": 151, "speaker": "PARIS", "text": "Sir\n              ,\n               \n              I\n               \n              propose\n               \n              not\n               \n              merely\n               \n              to\n               \n              myself"}, {"line_id": 152, "speaker": "PARIS", "text": "The\n               \n              pleasures\n               \n              such\n               \n              a\n               \n              beauty\n               \n              brings\n               \n              with\n               \n              it\n              ,"}, {"line_id": 153, "speaker": "PARIS", "text": "But\n               \n              I\n               \n              would\n               \n              have\n               \n              the\n               \n              soil\n               \n              of\n               \n              her\n               \n              fair\n               \n              rape"}, {"line_id": 154, "speaker": "PARIS", "text": "Wiped\n               \n              off\n               \n              in\n               \n              honorable\n               \n              keeping\n               \n              her\n              ."}, {"line_id": 155, "speaker": "PARIS", "text": "What\n               \n              treason\n               \n              were\n               \n              it\n               \n              to\n               \n              the\n               \n              ransacked\n               \n              queen\n              ,"}, {"line_id": 156, "speaker": "PARIS", "text": "Disgrace\n               \n              to\n               \n              your\n               \n              great\n               \n              worths\n              ,\n               \n              and\n               \n              shame\n               \n              to\n               \n              me\n              ,"}, {"line_id": 157, "speaker": "PARIS", "text": "Now\n               \n              to\n               \n              deliver\n               \n              her\n               \n              possession\n               \n              up"}, {"line_id": 158, "speaker": "PARIS", "text": "On\n               \n              terms\n               \n              of\n               \n              base\n               \n              compulsion\n              ?\n               \n              Can\n               \n              it\n               \n              be"}, {"line_id": 159, "speaker": "PARIS", "text": "That\n               \n              so\n               \n              degenerate\n               \n              a\n               \n              strain\n               \n              as\n               \n              this"}, {"line_id": 160, "speaker": "PARIS", "text": "Should\n               \n              once\n               \n              set\n               \n              footing\n               \n              in\n               \n              your\n               \n              generous\n               \n              bosoms\n              ?"}, {"line_id": 161, "speaker": "PARIS", "text": "There’s\n               \n              not\n               \n              the\n               \n              meanest\n               \n              spirit\n               \n              on\n               \n              our\n               \n              party"}, {"line_id": 162, "speaker": "PARIS", "text": "Without\n               \n              a\n               \n              heart\n               \n              to\n               \n              dare\n               \n              or\n               \n              sword\n               \n              to\n               \n              draw"}, {"line_id": 163, "speaker": "PARIS", "text": "When\n               \n              Helen\n               \n              is\n               \n              defended\n              ,\n               \n              nor\n               \n              none\n               \n              so\n               \n              noble"}, {"line_id": 164, "speaker": "PARIS", "text": "Whose\n               \n              life\n               \n              were\n               \n              ill\n               \n              bestowed\n               \n              or\n               \n              death\n               \n              unfamed"}, {"line_id": 165, "speaker": "PARIS", "text": "Where\n               \n              Helen\n               \n              is\n               \n              the\n               \n              subject\n              .\n               \n              Then\n               \n              I\n               \n              say\n              ,"}, {"line_id": 166, "speaker": "PARIS", "text": "Well\n               \n              may\n               \n              we\n               \n              fight\n               \n              for\n               \n              her\n               \n              whom\n              ,\n               \n              we\n               \n              know\n               \n              well\n              ,"}, {"line_id": 167, "speaker": "PARIS", "text": "The\n               \n              world’s\n               \n              large\n               \n              spaces\n               \n              cannot\n               \n              parallel\n              ."}, {"line_id": 168, "speaker": "HECTOR", "text": "Paris\n               \n              and\n               \n              Troilus\n              ,\n               \n              you\n               \n              have\n               \n              both\n               \n              said\n               \n              well\n              ,"}, {"line_id": 169, "speaker": "HECTOR", "text": "And\n               \n              on\n               \n              the\n               \n              cause\n               \n              and\n               \n              question\n               \n              now\n               \n              in\n               \n              hand"}, {"line_id": 170, "speaker": "HECTOR", "text": "Have\n               \n              glozed\n              —\n              but\n               \n              superficially\n              ,\n               \n              not\n               \n              much"}, {"line_id": 171, "speaker": "HECTOR", "text": "Unlike\n               \n              young\n               \n              men\n              ,\n               \n              whom\n               \n              Aristotle\n               \n              thought"}, {"line_id": 172, "speaker": "HECTOR", "text": "Unfit\n               \n              to\n               \n              hear\n               \n              moral\n               \n              philosophy\n              ."}, {"line_id": 173, "speaker": "HECTOR", "text": "The\n               \n              reasons\n               \n              you\n               \n              allege\n               \n              do\n               \n              more\n               \n              conduce"}, {"line_id": 174, "speaker": "HECTOR", "text": "To\n               \n              the\n               \n              hot\n               \n              passion\n               \n              of\n               \n              distempered\n               \n              blood"}, {"line_id": 175, "speaker": "HECTOR", "text": "Than\n               \n              to\n               \n              make\n               \n              up\n               \n              a\n               \n              free\n               \n              determination"}, {"line_id": 176, "speaker": "HECTOR", "text": "’Twixt\n               \n              right\n               \n              and\n               \n              wrong\n              ,\n               \n              for\n               \n              pleasure\n               \n              and\n               \n              revenge"}, {"line_id": 177, "speaker": "HECTOR", "text": "Have\n               \n              ears\n               \n              more\n               \n              deaf\n               \n              than\n               \n              adders\n               \n              to\n               \n              the\n               \n              voice"}, {"line_id": 178, "speaker": "HECTOR", "text": "Of\n               \n              any\n               \n              true\n               \n              decision\n              .\n               \n              Nature\n               \n              craves"}, {"line_id": 179, "speaker": "HECTOR", "text": "All\n               \n              dues\n               \n              be\n               \n              rendered\n               \n              to\n               \n              their\n               \n              owners\n              .\n               \n              Now\n              ,"}, {"line_id": 180, "speaker": "HECTOR", "text": "What\n               \n              nearer\n               \n              debt\n               \n              in\n               \n              all\n               \n              humanity"}, {"line_id": 181, "speaker": "HECTOR", "text": "Than\n               \n              wife\n               \n              is\n               \n              to\n               \n              the\n               \n              husband\n              ?\n               \n              If\n               \n              this\n               \n              law"}, {"line_id": 182, "speaker": "HECTOR", "text": "Of\n               \n              nature\n               \n              be\n               \n              corrupted\n               \n              through\n               \n              affection\n              ,"}, {"line_id": 183, "speaker": "HECTOR", "text": "And\n               \n              that\n               \n              great\n               \n              minds\n              ,\n               \n              of\n               \n              partial\n               \n              indulgence"}, {"line_id": 184, "speaker": "HECTOR", "text": "To\n               \n              their\n               \n              benumbèd\n               \n              wills\n              ,\n               \n              resist\n               \n              the\n               \n              same\n              ,"}, {"line_id": 185, "speaker": "HECTOR", "text": "There\n               \n              is\n               \n              a\n               \n              law\n               \n              in\n               \n              each\n               \n              well-ordered\n               \n              nation"}, {"line_id": 186, "speaker": "HECTOR", "text": "To\n               \n              curb\n               \n              those\n               \n              raging\n               \n              appetites\n               \n              that\n               \n              are"}, {"line_id": 187, "speaker": "HECTOR", "text": "Most\n               \n              disobedient\n               \n              and\n               \n              refractory\n              ."}, {"line_id": 188, "speaker": "HECTOR", "text": "If\n               \n              Helen\n              ,\n               \n              then\n              ,\n               \n              be\n               \n              wife\n               \n              to\n               \n              Sparta’s\n               \n              king\n              ,"}, {"line_id": 189, "speaker": "HECTOR", "text": "As\n               \n              it\n               \n              is\n               \n              known\n               \n              she\n               \n              is\n              ,\n               \n              these\n               \n              moral\n               \n              laws"}, {"line_id": 190, "speaker": "HECTOR", "text": "Of\n               \n              nature\n               \n              and\n               \n              of\n               \n              nations\n               \n              speak\n               \n              aloud"}, {"line_id": 191, "speaker": "HECTOR", "text": "To\n               \n              have\n               \n              her\n               \n              back\n               \n              returned\n              .\n               \n              Thus\n               \n              to\n               \n              persist"}, {"line_id": 192, "speaker": "HECTOR", "text": "In\n               \n              doing\n               \n              wrong\n               \n              extenuates\n               \n              not\n               \n              wrong\n              ,"}, {"line_id": 193, "speaker": "HECTOR", "text": "But\n               \n              makes\n               \n              it\n               \n              much\n               \n              more\n               \n              heavy\n              .\n               \n              Hector’s\n               \n              opinion"}, {"line_id": 194, "speaker": "HECTOR", "text": "Is\n               \n              this\n               \n              in\n               \n              way\n               \n              of\n               \n              truth\n              ;\n               \n              yet\n              ,\n               \n              ne’ertheless\n              ,"}, {"line_id": 195, "speaker": "HECTOR", "text": "My\n               \n              sprightly\n               \n              brethren\n              ,\n               \n              I\n               \n              propend\n               \n              to\n               \n              you"}, {"line_id": 196, "speaker": "HECTOR", "text": "In\n               \n              resolution\n               \n              to\n               \n              keep\n               \n              Helen\n               \n              still\n              ,"}, {"line_id": 197, "speaker": "HECTOR", "text": "For\n               \n              ’tis\n               \n              a\n               \n              cause\n               \n              that\n               \n              hath\n               \n              no\n               \n              mean\n               \n              dependence"}, {"line_id": 198, "speaker": "HECTOR", "text": "Upon\n               \n              our\n               \n              joint\n               \n              and\n               \n              several\n               \n              dignities\n              ."}, {"line_id": 199, "speaker": "TROILUS", "text": "Why\n              ,\n               \n              there\n               \n              you\n               \n              touched\n               \n              the\n               \n              life\n               \n              of\n               \n              our\n               \n              design\n              !"}, {"line_id": 200, "speaker": "TROILUS", "text": "Were\n               \n              it\n               \n              not\n               \n              glory\n               \n              that\n               \n              we\n               \n              more\n               \n              affected"}, {"line_id": 201, "speaker": "TROILUS", "text": "Than\n               \n              the\n               \n              performance\n               \n              of\n               \n              our\n               \n              heaving\n               \n              spleens\n              ,"}, {"line_id": 202, "speaker": "TROILUS", "text": "I\n               \n              would\n               \n              not\n               \n              wish\n               \n              a\n               \n              drop\n               \n              of\n               \n              Trojan\n               \n              blood"}, {"line_id": 203, "speaker": "TROILUS", "text": "Spent\n               \n              more\n               \n              in\n               \n              her\n               \n              defense\n              .\n               \n              But\n              ,\n               \n              worthy\n               \n              Hector\n              ,"}, {"line_id": 204, "speaker": "TROILUS", "text": "She\n               \n              is\n               \n              a\n               \n              theme\n               \n              of\n               \n              honor\n               \n              and\n               \n              renown\n              ,"}, {"line_id": 205, "speaker": "TROILUS", "text": "A\n               \n              spur\n               \n              to\n               \n              valiant\n               \n              and\n               \n              magnanimous\n               \n              deeds\n              ,"}, {"line_id": 206, "speaker": "TROILUS", "text": "Whose\n               \n              present\n               \n              courage\n               \n              may\n               \n              beat\n               \n              down\n               \n              our\n               \n              foes\n              ,"}, {"line_id": 207, "speaker": "TROILUS", "text": "And\n               \n              fame\n               \n              in\n               \n              time\n               \n              to\n               \n              come\n               \n              canonize\n               \n              us\n              ;"}, {"line_id": 208, "speaker": "TROILUS", "text": "For\n               \n              I\n               \n              presume\n               \n              brave\n               \n              Hector\n               \n              would\n               \n              not\n               \n              lose"}, {"line_id": 209, "speaker": "TROILUS", "text": "So\n               \n              rich\n               \n              advantage\n               \n              of\n               \n              a\n               \n              promised\n               \n              glory"}, {"line_id": 210, "speaker": "TROILUS", "text": "As\n               \n              smiles\n               \n              upon\n               \n              the\n               \n              forehead\n               \n              of\n               \n              this\n               \n              action"}, {"line_id": 211, "speaker": "TROILUS", "text": "For\n               \n              the\n               \n              wide\n               \n              world’s\n               \n              revenue\n              ."}, {"line_id": 212, "speaker": "HECTOR", "text": "I\n               \n              am\n               \n              yours\n              ,"}, {"line_id": 213, "speaker": "HECTOR", "text": "You\n               \n              valiant\n               \n              offspring\n               \n              of\n               \n              great\n               \n              Priamus\n              ."}, {"line_id": 214, "speaker": "HECTOR", "text": "I\n               \n              have\n               \n              a\n               \n              roisting\n               \n              challenge\n               \n              sent\n               \n              amongst"}, {"line_id": 215, "speaker": "HECTOR", "text": "The\n               \n              dull\n               \n              and\n               \n              factious\n               \n              nobles\n               \n              of\n               \n              the\n               \n              Greeks"}, {"line_id": 216, "speaker": "HECTOR", "text": "Will\n               \n              strike\n               \n              amazement\n               \n              to\n               \n              their\n               \n              drowsy\n               \n              spirits\n              ."}, {"line_id": 217, "speaker": "HECTOR", "text": "I\n               \n              was\n               \n              advertised\n               \n              their\n               \n              great\n               \n              general\n               \n              slept\n              ,"}, {"line_id": 218, "speaker": "HECTOR", "text": "Whilst\n               \n              emulation\n               \n              in\n               \n              the\n               \n              army\n               \n              crept\n              ."}, {"line_id": 219, "speaker": "HECTOR", "text": "This\n              ,\n               \n              I\n               \n              presume\n              ,\n               \n              will\n               \n              wake\n               \n              him\n              ."}]