[{"line_id": 1, "canonical_id": "ADO.4.1.1", "speaker": "LEONATO", "text": "Come, Friar Francis, be brief, only to the"}, {"line_id": 2, "canonical_id": "ADO.4.1.2", "speaker": "LEONATO", "text": "plain form of marriage, and you shall recount their"}, {"line_id": 3, "canonical_id": "ADO.4.1.3", "speaker": "LEONATO", "text": "particular duties afterwards."}, {"line_id": 4, "canonical_id": "ADO.4.1.4", "speaker": "FRIAR", "text": "You come hither, my lord, to marry"}, {"line_id": 5, "canonical_id": "ADO.4.1.5", "speaker": "FRIAR", "text": "this lady?"}, {"line_id": 6, "canonical_id": "ADO.4.1.6", "speaker": "CLAUDIO", "text": "No."}, {"line_id": 7, "canonical_id": "ADO.4.1.7", "speaker": "LEONATO", "text": "To be married to her.—Friar, you come to"}, {"line_id": 8, "canonical_id": "ADO.4.1.8", "speaker": "LEONATO", "text": "marry her."}, {"line_id": 9, "canonical_id": "ADO.4.1.9", "speaker": "FRIAR", "text": "Lady, you come hither to be married to this"}, {"line_id": 10, "canonical_id": "ADO.4.1.10", "speaker": "FRIAR", "text": "count?"}, {"line_id": 11, "canonical_id": "ADO.4.1.11", "speaker": "HERO", "text": "I do."}, {"line_id": 12, "canonical_id": "ADO.4.1.12", "speaker": "FRIAR", "text": "If either of you know any inward impediment"}, {"line_id": 13, "canonical_id": "ADO.4.1.13", "speaker": "FRIAR", "text": "why you should not be conjoined, I charge you on"}, {"line_id": 14, "canonical_id": "ADO.4.1.14", "speaker": "FRIAR", "text": "your souls to utter it."}, {"line_id": 15, "canonical_id": "ADO.4.1.15", "speaker": "CLAUDIO", "text": "Know you any, Hero?"}, {"line_id": 16, "canonical_id": "ADO.4.1.16", "speaker": "HERO", "text": "None, my lord."}, {"line_id": 17, "canonical_id": "ADO.4.1.17", "speaker": "FRIAR", "text": "Know you any, count?"}, {"line_id": 18, "canonical_id": "ADO.4.1.18", "speaker": "LEONATO", "text": "I dare make his answer, none."}, {"line_id": 19, "canonical_id": "ADO.4.1.19", "speaker": "CLAUDIO", "text": "O, what men dare do! What men may do!"}, {"line_id": 20, "canonical_id": "ADO.4.1.20", "speaker": "CLAUDIO", "text": "What men daily do, not knowing what they do!"}, {"line_id": 21, "canonical_id": "ADO.4.1.21", "speaker": "BENEDICK", "text": "How now, interjections? Why, then, some"}, {"line_id": 22, "canonical_id": "ADO.4.1.22", "speaker": "BENEDICK", "text": "be of laughing, as ah, ha, he!"}, {"line_id": 23, "canonical_id": "ADO.4.1.23", "speaker": "CLAUDIO", "text": "Stand\n               \n              thee\n               \n              by\n              ,\n               \n              friar\n              .\n              —\n              Father\n              ,\n               \n              by\n               \n              your\n               \n              leave\n              ,"}, {"line_id": 24, "canonical_id": "ADO.4.1.24", "speaker": "CLAUDIO", "text": "Will\n               \n              you\n               \n              with\n               \n              free\n               \n              and\n               \n              unconstrainèd\n               \n              soul"}, {"line_id": 25, "canonical_id": "ADO.4.1.25", "speaker": "CLAUDIO", "text": "Give\n               \n              me\n               \n              this\n               \n              maid\n              ,\n               \n              your\n               \n              daughter\n              ?"}, {"line_id": 26, "canonical_id": "ADO.4.1.26", "speaker": "LEONATO", "text": "As\n               \n              freely\n              ,\n               \n              son\n              ,\n               \n              as\n               \n              God\n               \n              did\n               \n              give\n               \n              her\n               \n              me\n              ."}, {"line_id": 27, "canonical_id": "ADO.4.1.27", "speaker": "CLAUDIO", "text": "And\n               \n              what\n               \n              have\n               \n              I\n               \n              to\n               \n              give\n               \n              you\n               \n              back\n               \n              whose\n               \n              worth"}, {"line_id": 28, "canonical_id": "ADO.4.1.28", "speaker": "CLAUDIO", "text": "May\n               \n              counterpoise\n               \n              this\n               \n              rich\n               \n              and\n               \n              precious\n               \n              gift\n              ?"}, {"line_id": 29, "canonical_id": "ADO.4.1.29", "speaker": "PRINCE", "text": "Nothing\n              ,\n               \n              unless\n               \n              you\n               \n              render\n               \n              her\n               \n              again\n              ."}, {"line_id": 30, "canonical_id": "ADO.4.1.30", "speaker": "CLAUDIO", "text": "Sweet\n               \n              prince\n              ,\n               \n              you\n               \n              learn\n               \n              me\n               \n              noble\n               \n              thankfulness\n              .\n              —"}, {"line_id": 31, "canonical_id": "ADO.4.1.31", "speaker": "CLAUDIO", "text": "There\n              ,\n               \n              Leonato\n              ,\n               \n              take\n               \n              her\n               \n              back\n               \n              again\n              ."}, {"line_id": 32, "canonical_id": "ADO.4.1.32", "speaker": "CLAUDIO", "text": "Give\n               \n              not\n               \n              this\n               \n              rotten\n               \n              orange\n               \n              to\n               \n              your\n               \n              friend\n              ."}, {"line_id": 33, "canonical_id": "ADO.4.1.33", "speaker": "CLAUDIO", "text": "She’s\n               \n              but\n               \n              the\n               \n              sign\n               \n              and\n               \n              semblance\n               \n              of\n               \n              her\n               \n              honor\n              ."}, {"line_id": 34, "canonical_id": "ADO.4.1.34", "speaker": "CLAUDIO", "text": "Behold\n               \n              how\n               \n              like\n               \n              a\n               \n              maid\n               \n              she\n               \n              blushes\n               \n              here\n              !"}, {"line_id": 35, "canonical_id": "ADO.4.1.35", "speaker": "CLAUDIO", "text": "O\n              ,\n               \n              what\n               \n              authority\n               \n              and\n               \n              show\n               \n              of\n               \n              truth"}, {"line_id": 36, "canonical_id": "ADO.4.1.36", "speaker": "CLAUDIO", "text": "Can\n               \n              cunning\n               \n              sin\n               \n              cover\n               \n              itself\n               \n              withal\n              !"}, {"line_id": 37, "canonical_id": "ADO.4.1.37", "speaker": "CLAUDIO", "text": "Comes\n               \n              not\n               \n              that\n               \n              blood\n               \n              as\n               \n              modest\n               \n              evidence"}, {"line_id": 38, "canonical_id": "ADO.4.1.38", "speaker": "CLAUDIO", "text": "To\n               \n              witness\n               \n              simple\n               \n              virtue\n              ?\n               \n              Would\n               \n              you\n               \n              not\n               \n              swear\n              ,"}, {"line_id": 39, "canonical_id": "ADO.4.1.39", "speaker": "CLAUDIO", "text": "All\n               \n              you\n               \n              that\n               \n              see\n               \n              her\n              ,\n               \n              that\n               \n              she\n               \n              were\n               \n              a\n               \n              maid\n              ,"}, {"line_id": 40, "canonical_id": "ADO.4.1.40", "speaker": "CLAUDIO", "text": "By\n               \n              these\n               \n              exterior\n               \n              shows\n              ?\n               \n              But\n               \n              she\n               \n              is\n               \n              none\n              ."}, {"line_id": 41, "canonical_id": "ADO.4.1.41", "speaker": "CLAUDIO", "text": "She\n               \n              knows\n               \n              the\n               \n              heat\n               \n              of\n               \n              a\n               \n              luxurious\n               \n              bed\n              ."}, {"line_id": 42, "canonical_id": "ADO.4.1.42", "speaker": "CLAUDIO", "text": "Her\n               \n              blush\n               \n              is\n               \n              guiltiness\n              ,\n               \n              not\n               \n              modesty\n              ."}, {"line_id": 43, "canonical_id": "ADO.4.1.43", "speaker": "LEONATO", "text": "What\n               \n              do\n               \n              you\n               \n              mean\n              ,\n               \n              my\n               \n              lord\n              ?"}, {"line_id": 44, "canonical_id": "ADO.4.1.44", "speaker": "CLAUDIO", "text": "Not\n               \n              to\n               \n              be\n               \n              married\n              ,"}, {"line_id": 45, "canonical_id": "ADO.4.1.45", "speaker": "CLAUDIO", "text": "Not\n               \n              to\n               \n              knit\n               \n              my\n               \n              soul\n               \n              to\n               \n              an\n               \n              approvèd\n               \n              wanton\n              ."}, {"line_id": 46, "canonical_id": "ADO.4.1.46", "speaker": "LEONATO", "text": "Dear\n               \n              my\n               \n              lord\n              ,\n               \n              if\n               \n              you\n               \n              in\n               \n              your\n               \n              own\n               \n              proof"}, {"line_id": 47, "canonical_id": "ADO.4.1.47", "speaker": "LEONATO", "text": "Have\n               \n              vanquished\n               \n              the\n               \n              resistance\n               \n              of\n               \n              her\n               \n              youth\n              ,"}, {"line_id": 48, "canonical_id": "ADO.4.1.48", "speaker": "LEONATO", "text": "And\n               \n              made\n               \n              defeat\n               \n              of\n               \n              her\n               \n              virginity\n              —"}, {"line_id": 49, "canonical_id": "ADO.4.1.49", "speaker": "CLAUDIO", "text": "I\n               \n              know\n               \n              what\n               \n              you\n               \n              would\n               \n              say\n              :\n               \n              if\n               \n              I\n               \n              have\n               \n              known\n               \n              her\n              ,"}, {"line_id": 50, "canonical_id": "ADO.4.1.50", "speaker": "CLAUDIO", "text": "You\n               \n              will\n               \n              say\n               \n              she\n               \n              did\n               \n              embrace\n               \n              me\n               \n              as\n               \n              a\n               \n              husband\n              ,"}, {"line_id": 51, "canonical_id": "ADO.4.1.51", "speaker": "CLAUDIO", "text": "And\n               \n              so\n               \n              extenuate\n               \n              the\n               \n              forehand\n               \n              sin\n              ."}, {"line_id": 52, "canonical_id": "ADO.4.1.52", "speaker": "CLAUDIO", "text": "No\n              ,\n               \n              Leonato\n              ,"}, {"line_id": 53, "canonical_id": "ADO.4.1.53", "speaker": "CLAUDIO", "text": "I\n               \n              never\n               \n              tempted\n               \n              her\n               \n              with\n               \n              word\n               \n              too\n               \n              large\n              ,"}, {"line_id": 54, "canonical_id": "ADO.4.1.54", "speaker": "CLAUDIO", "text": "But\n              ,\n               \n              as\n               \n              a\n               \n              brother\n               \n              to\n               \n              his\n               \n              sister\n              ,\n               \n              showed"}, {"line_id": 55, "canonical_id": "ADO.4.1.55", "speaker": "CLAUDIO", "text": "Bashful\n               \n              sincerity\n               \n              and\n               \n              comely\n               \n              love\n              ."}, {"line_id": 56, "canonical_id": "ADO.4.1.56", "speaker": "HERO", "text": "And\n               \n              seemed\n               \n              I\n               \n              ever\n               \n              otherwise\n               \n              to\n               \n              you\n              ?"}, {"line_id": 57, "canonical_id": "ADO.4.1.57", "speaker": "CLAUDIO", "text": "Out\n               \n              on\n               \n              thee\n              ,\n               \n              seeming\n              !\n               \n              I\n               \n              will\n               \n              write\n               \n              against\n               \n              it\n              ."}, {"line_id": 58, "canonical_id": "ADO.4.1.58", "speaker": "CLAUDIO", "text": "You\n               \n              seem\n               \n              to\n               \n              me\n               \n              as\n               \n              Dian\n               \n              in\n               \n              her\n               \n              orb\n              ,"}, {"line_id": 59, "canonical_id": "ADO.4.1.59", "speaker": "CLAUDIO", "text": "As\n               \n              chaste\n               \n              as\n               \n              is\n               \n              the\n               \n              bud\n               \n              ere\n               \n              it\n               \n              be\n               \n              blown\n              ."}, {"line_id": 60, "canonical_id": "ADO.4.1.60", "speaker": "CLAUDIO", "text": "But\n               \n              you\n               \n              are\n               \n              more\n               \n              intemperate\n               \n              in\n               \n              your\n               \n              blood"}, {"line_id": 61, "canonical_id": "ADO.4.1.61", "speaker": "CLAUDIO", "text": "Than\n               \n              Venus\n              ,\n               \n              or\n               \n              those\n               \n              pampered\n               \n              animals"}, {"line_id": 62, "canonical_id": "ADO.4.1.62", "speaker": "CLAUDIO", "text": "That\n               \n              rage\n               \n              in\n               \n              savage\n               \n              sensuality\n              ."}, {"line_id": 63, "canonical_id": "ADO.4.1.63", "speaker": "HERO", "text": "Is\n               \n              my\n               \n              lord\n               \n              well\n               \n              that\n               \n              he\n               \n              doth\n               \n              speak\n               \n              so\n               \n              wide\n              ?"}, {"line_id": 64, "canonical_id": "ADO.4.1.64", "speaker": "LEONATO", "text": "Sweet\n               \n              prince\n              ,\n               \n              why\n               \n              speak\n               \n              not\n               \n              you\n              ?"}, {"line_id": 65, "canonical_id": "ADO.4.1.65", "speaker": "PRINCE", "text": "What\n               \n              should\n               \n              I\n               \n              speak\n              ?"}, {"line_id": 66, "canonical_id": "ADO.4.1.66", "speaker": "PRINCE", "text": "I\n               \n              stand\n               \n              dishonored\n               \n              that\n               \n              have\n               \n              gone\n               \n              about"}, {"line_id": 67, "canonical_id": "ADO.4.1.67", "speaker": "PRINCE", "text": "To\n               \n              link\n               \n              my\n               \n              dear\n               \n              friend\n               \n              to\n               \n              a\n               \n              common\n               \n              stale\n              ."}, {"line_id": 68, "canonical_id": "ADO.4.1.68", "speaker": "LEONATO", "text": "Are\n               \n              these\n               \n              things\n               \n              spoken\n              ,\n               \n              or\n               \n              do\n               \n              I\n               \n              but\n               \n              dream\n              ?"}, {"line_id": 69, "canonical_id": "ADO.4.1.69", "speaker": "DON\n               \n              JOHN", "text": "Sir\n              ,\n               \n              they\n               \n              are\n               \n              spoken\n              ,\n               \n              and\n               \n              these\n               \n              things\n               \n              are\n               \n              true\n              ."}, {"line_id": 70, "canonical_id": "ADO.4.1.70", "speaker": "BENEDICK", "text": "This\n               \n              looks\n               \n              not\n               \n              like\n               \n              a\n               \n              nuptial\n              ."}, {"line_id": 71, "canonical_id": "ADO.4.1.71", "speaker": "HERO", "text": "True\n              !\n               \n              O\n               \n              God\n              !"}, {"line_id": 72, "canonical_id": "ADO.4.1.72", "speaker": "CLAUDIO", "text": "Leonato\n              ,\n               \n              stand\n               \n              I\n               \n              here\n              ?"}, {"line_id": 73, "canonical_id": "ADO.4.1.73", "speaker": "CLAUDIO", "text": "Is\n               \n              this\n               \n              the\n               \n              Prince\n              ?\n               \n              Is\n               \n              this\n               \n              the\n               \n              Prince’s\n               \n              brother\n              ?"}, {"line_id": 74, "canonical_id": "ADO.4.1.74", "speaker": "CLAUDIO", "text": "Is\n               \n              this\n               \n              face\n               \n              Hero’s\n              ?\n               \n              Are\n               \n              our\n               \n              eyes\n               \n              our\n               \n              own\n              ?"}, {"line_id": 75, "canonical_id": "ADO.4.1.75", "speaker": "LEONATO", "text": "All\n               \n              this\n               \n              is\n               \n              so\n              ,\n               \n              but\n               \n              what\n               \n              of\n               \n              this\n              ,\n               \n              my\n               \n              lord\n              ?"}, {"line_id": 76, "canonical_id": "ADO.4.1.76", "speaker": "CLAUDIO", "text": "Let\n               \n              me\n               \n              but\n               \n              move\n               \n              one\n               \n              question\n               \n              to\n               \n              your\n               \n              daughter\n              ,"}, {"line_id": 77, "canonical_id": "ADO.4.1.77", "speaker": "CLAUDIO", "text": "And\n               \n              by\n               \n              that\n               \n              fatherly\n               \n              and\n               \n              kindly\n               \n              power"}, {"line_id": 78, "canonical_id": "ADO.4.1.78", "speaker": "CLAUDIO", "text": "That\n               \n              you\n               \n              have\n               \n              in\n               \n              her\n              ,\n               \n              bid\n               \n              her\n               \n              answer\n               \n              truly\n              ."}, {"line_id": 79, "canonical_id": "ADO.4.1.79", "speaker": "LEONATO", "text": "I\n               \n              charge\n               \n              thee\n               \n              do\n               \n              so\n              ,\n               \n              as\n               \n              thou\n               \n              art\n               \n              my\n               \n              child\n              ."}, {"line_id": 80, "canonical_id": "ADO.4.1.80", "speaker": "HERO", "text": "O\n              ,\n               \n              God\n               \n              defend\n               \n              me\n              ,\n               \n              how\n               \n              am\n               \n              I\n               \n              beset\n              !\n              —"}, {"line_id": 81, "canonical_id": "ADO.4.1.81", "speaker": "HERO", "text": "What\n               \n              kind\n               \n              of\n               \n              catechizing\n               \n              call\n               \n              you\n               \n              this\n              ?"}, {"line_id": 82, "canonical_id": "ADO.4.1.82", "speaker": "CLAUDIO", "text": "To\n               \n              make\n               \n              you\n               \n              answer\n               \n              truly\n               \n              to\n               \n              your\n               \n              name\n              ."}, {"line_id": 83, "canonical_id": "ADO.4.1.83", "speaker": "HERO", "text": "Is\n               \n              it\n               \n              not\n               \n              Hero\n              ?\n               \n              Who\n               \n              can\n               \n              blot\n               \n              that\n               \n              name"}, {"line_id": 84, "canonical_id": "ADO.4.1.84", "speaker": "HERO", "text": "With\n               \n              any\n               \n              just\n               \n              reproach\n              ?"}, {"line_id": 85, "canonical_id": "ADO.4.1.85", "speaker": "CLAUDIO", "text": "Marry\n              ,\n               \n              that\n               \n              can\n               \n              Hero\n              !"}, {"line_id": 86, "canonical_id": "ADO.4.1.86", "speaker": "CLAUDIO", "text": "Hero\n               \n              itself\n               \n              can\n               \n              blot\n               \n              out\n               \n              Hero’s\n               \n              virtue\n              ."}, {"line_id": 87, "canonical_id": "ADO.4.1.87", "speaker": "CLAUDIO", "text": "What\n               \n              man\n               \n              was\n               \n              he\n               \n              talked\n               \n              with\n               \n              you\n               \n              yesternight"}, {"line_id": 88, "canonical_id": "ADO.4.1.88", "speaker": "CLAUDIO", "text": "Out\n               \n              at\n               \n              your\n               \n              window\n               \n              betwixt\n               \n              twelve\n               \n              and\n               \n              one\n              ?"}, {"line_id": 89, "canonical_id": "ADO.4.1.89", "speaker": "CLAUDIO", "text": "Now\n              ,\n               \n              if\n               \n              you\n               \n              are\n               \n              a\n               \n              maid\n              ,\n               \n              answer\n               \n              to\n               \n              this\n              ."}, {"line_id": 90, "canonical_id": "ADO.4.1.90", "speaker": "HERO", "text": "I\n               \n              talked\n               \n              with\n               \n              no\n               \n              man\n               \n              at\n               \n              that\n               \n              hour\n              ,\n               \n              my\n               \n              lord\n              ."}, {"line_id": 91, "canonical_id": "ADO.4.1.91", "speaker": "PRINCE", "text": "Why\n              ,\n               \n              then\n              ,\n               \n              are\n               \n              you\n               \n              no\n               \n              maiden\n              .\n              —\n              Leonato\n              ,"}, {"line_id": 92, "canonical_id": "ADO.4.1.92", "speaker": "PRINCE", "text": "I\n               \n              am\n               \n              sorry\n               \n              you\n               \n              must\n               \n              hear\n              .\n               \n              Upon\n               \n              mine\n               \n              honor\n              ,"}, {"line_id": 93, "canonical_id": "ADO.4.1.93", "speaker": "PRINCE", "text": "Myself\n              ,\n               \n              my\n               \n              brother\n              ,\n               \n              and\n               \n              this\n               \n              grievèd\n               \n              count"}, {"line_id": 94, "canonical_id": "ADO.4.1.94", "speaker": "PRINCE", "text": "Did\n               \n              see\n               \n              her\n              ,\n               \n              hear\n               \n              her\n              ,\n               \n              at\n               \n              that\n               \n              hour\n               \n              last\n               \n              night"}, {"line_id": 95, "canonical_id": "ADO.4.1.95", "speaker": "PRINCE", "text": "Talk\n               \n              with\n               \n              a\n               \n              ruffian\n               \n              at\n               \n              her\n               \n              chamber\n               \n              window\n              ,"}, {"line_id": 96, "canonical_id": "ADO.4.1.96", "speaker": "PRINCE", "text": "Who\n               \n              hath\n               \n              indeed\n              ,\n               \n              most\n               \n              like\n               \n              a\n               \n              liberal\n               \n              villain\n              ,"}, {"line_id": 97, "canonical_id": "ADO.4.1.97", "speaker": "PRINCE", "text": "Confessed\n               \n              the\n               \n              vile\n               \n              encounters\n               \n              they\n               \n              have\n               \n              had"}, {"line_id": 98, "canonical_id": "ADO.4.1.98", "speaker": "PRINCE", "text": "A\n               \n              thousand\n               \n              times\n               \n              in\n               \n              secret\n              ."}, {"line_id": 99, "canonical_id": "ADO.4.1.99", "speaker": "DON\n               \n              JOHN", "text": "Fie\n              ,\n               \n              fie\n              ,\n               \n              they\n               \n              are\n               \n              not\n               \n              to\n               \n              be\n               \n              named\n              ,\n               \n              my\n               \n              lord\n              ,"}, {"line_id": 100, "canonical_id": "ADO.4.1.100", "speaker": "DON\n               \n              JOHN", "text": "Not\n               \n              to\n               \n              be\n               \n              spoke\n               \n              of\n              !"}, {"line_id": 101, "canonical_id": "ADO.4.1.101", "speaker": "DON\n               \n              JOHN", "text": "There\n               \n              is\n               \n              not\n               \n              chastity\n               \n              enough\n               \n              in\n               \n              language\n              ,"}, {"line_id": 102, "canonical_id": "ADO.4.1.102", "speaker": "DON\n               \n              JOHN", "text": "Without\n               \n              offense\n              ,\n               \n              to\n               \n              utter\n               \n              them\n              .\n              —\n              Thus\n              ,\n               \n              pretty\n               \n              lady\n              ,"}, {"line_id": 103, "canonical_id": "ADO.4.1.103", "speaker": "DON\n               \n              JOHN", "text": "I\n               \n              am\n               \n              sorry\n               \n              for\n               \n              thy\n               \n              much\n               \n              misgovernment\n              ."}, {"line_id": 104, "canonical_id": "ADO.4.1.104", "speaker": "CLAUDIO", "text": "O\n               \n              Hero\n              ,\n               \n              what\n               \n              a\n               \n              Hero\n               \n              hadst\n               \n              thou\n               \n              been"}, {"line_id": 105, "canonical_id": "ADO.4.1.105", "speaker": "CLAUDIO", "text": "If\n               \n              half\n               \n              thy\n               \n              outward\n               \n              graces\n               \n              had\n               \n              been\n               \n              placed"}, {"line_id": 106, "canonical_id": "ADO.4.1.106", "speaker": "CLAUDIO", "text": "About\n               \n              thy\n               \n              thoughts\n               \n              and\n               \n              counsels\n               \n              of\n               \n              thy\n               \n              heart\n              !"}, {"line_id": 107, "canonical_id": "ADO.4.1.107", "speaker": "CLAUDIO", "text": "But\n               \n              fare\n               \n              thee\n               \n              well\n              ,\n               \n              most\n               \n              foul\n              ,\n               \n              most\n               \n              fair\n              .\n               \n              Farewell\n              ,"}, {"line_id": 108, "canonical_id": "ADO.4.1.108", "speaker": "CLAUDIO", "text": "Thou\n               \n              pure\n               \n              impiety\n               \n              and\n               \n              impious\n               \n              purity\n              ."}, {"line_id": 109, "canonical_id": "ADO.4.1.109", "speaker": "CLAUDIO", "text": "For\n               \n              thee\n               \n              I’ll\n               \n              lock\n               \n              up\n               \n              all\n               \n              the\n               \n              gates\n               \n              of\n               \n              love"}, {"line_id": 110, "canonical_id": "ADO.4.1.110", "speaker": "CLAUDIO", "text": "And\n               \n              on\n               \n              my\n               \n              eyelids\n               \n              shall\n               \n              conjecture\n               \n              hang\n              ,"}, {"line_id": 111, "canonical_id": "ADO.4.1.111", "speaker": "CLAUDIO", "text": "To\n               \n              turn\n               \n              all\n               \n              beauty\n               \n              into\n               \n              thoughts\n               \n              of\n               \n              harm\n              ,"}, {"line_id": 112, "canonical_id": "ADO.4.1.112", "speaker": "CLAUDIO", "text": "And\n               \n              never\n               \n              shall\n               \n              it\n               \n              more\n               \n              be\n               \n              gracious\n              ."}, {"line_id": 113, "canonical_id": "ADO.4.1.113", "speaker": "LEONATO", "text": "Hath\n               \n              no\n               \n              man’s\n               \n              dagger\n               \n              here\n               \n              a\n               \n              point\n               \n              for\n               \n              me\n              ?"}, {"line_id": 114, "canonical_id": "ADO.4.1.114", "speaker": "BEATRICE", "text": "Why\n              ,\n               \n              how\n               \n              now\n              ,\n               \n              cousin\n              ,\n               \n              wherefore\n               \n              sink\n               \n              you\n               \n              down\n              ?"}, {"line_id": 115, "canonical_id": "ADO.4.1.115", "speaker": "DON\n               \n              JOHN", "text": "Come\n              ,\n               \n              let\n               \n              us\n               \n              go\n              .\n               \n              These\n               \n              things\n              ,\n               \n              come\n               \n              thus\n               \n              to\n               \n              light\n              ,"}, {"line_id": 116, "canonical_id": "ADO.4.1.116", "speaker": "DON\n               \n              JOHN", "text": "Smother\n               \n              her\n               \n              spirits\n               \n              up\n              ."}, {"line_id": 117, "canonical_id": "ADO.4.1.117", "speaker": "BENEDICK", "text": "How\n               \n              doth\n               \n              the\n               \n              lady\n              ?"}, {"line_id": 118, "canonical_id": "ADO.4.1.118", "speaker": "BEATRICE", "text": "Dead\n              ,\n               \n              I\n               \n              think\n              .\n              —\n              Help\n              ,\n               \n              uncle\n              !\n              —"}, {"line_id": 119, "canonical_id": "ADO.4.1.119", "speaker": "BEATRICE", "text": "Hero\n              ,\n               \n              why\n               \n              Hero\n              !\n               \n              Uncle\n              !\n               \n              Signior\n               \n              Benedick\n              !\n               \n              Friar\n              !"}, {"line_id": 120, "canonical_id": "ADO.4.1.120", "speaker": "LEONATO", "text": "O\n               \n              Fate\n              ,\n               \n              take\n               \n              not\n               \n              away\n               \n              thy\n               \n              heavy\n               \n              hand\n              !"}, {"line_id": 121, "canonical_id": "ADO.4.1.121", "speaker": "LEONATO", "text": "Death\n               \n              is\n               \n              the\n               \n              fairest\n               \n              cover\n               \n              for\n               \n              her\n               \n              shame"}, {"line_id": 122, "canonical_id": "ADO.4.1.122", "speaker": "LEONATO", "text": "That\n               \n              may\n               \n              be\n               \n              wished\n               \n              for\n              ."}, {"line_id": 123, "canonical_id": "ADO.4.1.123", "speaker": "BEATRICE", "text": "How\n               \n              now\n              ,\n               \n              cousin\n               \n              Hero\n              ?"}, {"line_id": 124, "canonical_id": "ADO.4.1.124", "speaker": "FRIAR", "text": "Have\n               \n              comfort\n              ,\n               \n              lady\n              ."}, {"line_id": 125, "canonical_id": "ADO.4.1.125", "speaker": "LEONATO", "text": "Dost\n               \n              thou\n               \n              look\n               \n              up\n              ?"}, {"line_id": 126, "canonical_id": "ADO.4.1.126", "speaker": "FRIAR", "text": "Yea\n              ,\n               \n              wherefore\n               \n              should\n               \n              she\n               \n              not\n              ?"}, {"line_id": 127, "canonical_id": "ADO.4.1.127", "speaker": "LEONATO", "text": "Wherefore\n              ?\n               \n              Why\n              ,\n               \n              doth\n               \n              not\n               \n              every\n               \n              earthly\n               \n              thing"}, {"line_id": 128, "canonical_id": "ADO.4.1.128", "speaker": "LEONATO", "text": "Cry\n               \n              shame\n               \n              upon\n               \n              her\n              ?\n               \n              Could\n               \n              she\n               \n              here\n               \n              deny"}, {"line_id": 129, "canonical_id": "ADO.4.1.129", "speaker": "LEONATO", "text": "The\n               \n              story\n               \n              that\n               \n              is\n               \n              printed\n               \n              in\n               \n              her\n               \n              blood\n              ?\n              —"}, {"line_id": 130, "canonical_id": "ADO.4.1.130", "speaker": "LEONATO", "text": "Do\n               \n              not\n               \n              live\n              ,\n               \n              Hero\n              ,\n               \n              do\n               \n              not\n               \n              ope\n               \n              thine\n               \n              eyes\n              ,"}, {"line_id": 131, "canonical_id": "ADO.4.1.131", "speaker": "LEONATO", "text": "For\n              ,\n               \n              did\n               \n              I\n               \n              think\n               \n              thou\n               \n              wouldst\n               \n              not\n               \n              quickly\n               \n              die\n              ,"}, {"line_id": 132, "canonical_id": "ADO.4.1.132", "speaker": "LEONATO", "text": "Thought\n               \n              I\n               \n              thy\n               \n              spirits\n               \n              were\n               \n              stronger\n               \n              than\n               \n              thy\n               \n              shames\n              ,"}, {"line_id": 133, "canonical_id": "ADO.4.1.133", "speaker": "LEONATO", "text": "Myself\n               \n              would\n              ,\n               \n              on\n               \n              the\n               \n              rearward\n               \n              of\n               \n              reproaches\n              ,"}, {"line_id": 134, "canonical_id": "ADO.4.1.134", "speaker": "LEONATO", "text": "Strike\n               \n              at\n               \n              thy\n               \n              life\n              .\n               \n              Grieved\n               \n              I\n               \n              I\n               \n              had\n               \n              but\n               \n              one\n              ?"}, {"line_id": 135, "canonical_id": "ADO.4.1.135", "speaker": "LEONATO", "text": "Chid\n               \n              I\n               \n              for\n               \n              that\n               \n              at\n               \n              frugal\n               \n              Nature’s\n               \n              frame\n              ?"}, {"line_id": 136, "canonical_id": "ADO.4.1.136", "speaker": "LEONATO", "text": "O\n              ,\n               \n              one\n               \n              too\n               \n              much\n               \n              by\n               \n              thee\n              !\n               \n              Why\n               \n              had\n               \n              I\n               \n              one\n              ?"}, {"line_id": 137, "canonical_id": "ADO.4.1.137", "speaker": "LEONATO", "text": "Why\n               \n              ever\n               \n              wast\n               \n              thou\n               \n              lovely\n               \n              in\n               \n              my\n               \n              eyes\n              ?"}, {"line_id": 138, "canonical_id": "ADO.4.1.138", "speaker": "LEONATO", "text": "Why\n               \n              had\n               \n              I\n               \n              not\n               \n              with\n               \n              charitable\n               \n              hand"}, {"line_id": 139, "canonical_id": "ADO.4.1.139", "speaker": "LEONATO", "text": "Took\n               \n              up\n               \n              a\n               \n              beggar’s\n               \n              issue\n               \n              at\n               \n              my\n               \n              gates\n              ,"}, {"line_id": 140, "canonical_id": "ADO.4.1.140", "speaker": "LEONATO", "text": "Who\n              ,\n               \n              smirchèd\n               \n              thus\n              ,\n               \n              and\n               \n              mired\n               \n              with\n               \n              infamy\n              ,"}, {"line_id": 141, "canonical_id": "ADO.4.1.141", "speaker": "LEONATO", "text": "I\n               \n              might\n               \n              have\n               \n              said\n               \n              “\n              No\n               \n              part\n               \n              of\n               \n              it\n               \n              is\n               \n              mine\n              ;"}, {"line_id": 142, "canonical_id": "ADO.4.1.142", "speaker": "LEONATO", "text": "This\n               \n              shame\n               \n              derives\n               \n              itself\n               \n              from\n               \n              unknown\n               \n              loins\n              ”\n              ?"}, {"line_id": 143, "canonical_id": "ADO.4.1.143", "speaker": "LEONATO", "text": "But\n               \n              mine\n              ,\n               \n              and\n               \n              mine\n               \n              I\n               \n              loved\n              ,\n               \n              and\n               \n              mine\n               \n              I\n               \n              praised\n              ,"}, {"line_id": 144, "canonical_id": "ADO.4.1.144", "speaker": "LEONATO", "text": "And\n               \n              mine\n               \n              that\n               \n              I\n               \n              was\n               \n              proud\n               \n              on\n              ,\n               \n              mine\n               \n              so\n               \n              much"}, {"line_id": 145, "canonical_id": "ADO.4.1.145", "speaker": "LEONATO", "text": "That\n               \n              I\n               \n              myself\n               \n              was\n               \n              to\n               \n              myself\n               \n              not\n               \n              mine\n              ,"}, {"line_id": 146, "canonical_id": "ADO.4.1.146", "speaker": "LEONATO", "text": "Valuing\n               \n              of\n               \n              her\n              —\n              why\n               \n              she\n              ,\n               \n              O\n               \n              she\n              ,\n               \n              is\n               \n              fall’n"}, {"line_id": 147, "canonical_id": "ADO.4.1.147", "speaker": "LEONATO", "text": "Into\n               \n              a\n               \n              pit\n               \n              of\n               \n              ink\n              ,\n               \n              that\n               \n              the\n               \n              wide\n               \n              sea"}, {"line_id": 148, "canonical_id": "ADO.4.1.148", "speaker": "LEONATO", "text": "Hath\n               \n              drops\n               \n              too\n               \n              few\n               \n              to\n               \n              wash\n               \n              her\n               \n              clean\n               \n              again\n              ,"}, {"line_id": 149, "canonical_id": "ADO.4.1.149", "speaker": "LEONATO", "text": "And\n               \n              salt\n               \n              too\n               \n              little\n               \n              which\n               \n              may\n               \n              season\n               \n              give"}, {"line_id": 150, "canonical_id": "ADO.4.1.150", "speaker": "LEONATO", "text": "To\n               \n              her\n               \n              foul\n               \n              tainted\n               \n              flesh\n              !"}, {"line_id": 151, "canonical_id": "ADO.4.1.151", "speaker": "BENEDICK", "text": "Sir\n              ,\n               \n              sir\n              ,\n               \n              be\n               \n              patient\n              ."}, {"line_id": 152, "canonical_id": "ADO.4.1.152", "speaker": "BENEDICK", "text": "For\n               \n              my\n               \n              part\n              ,\n               \n              I\n               \n              am\n               \n              so\n               \n              attired\n               \n              in\n               \n              wonder"}, {"line_id": 153, "canonical_id": "ADO.4.1.153", "speaker": "BENEDICK", "text": "I\n               \n              know\n               \n              not\n               \n              what\n               \n              to\n               \n              say\n              ."}, {"line_id": 154, "canonical_id": "ADO.4.1.154", "speaker": "BEATRICE", "text": "O\n              ,\n               \n              on\n               \n              my\n               \n              soul\n              ,\n               \n              my\n               \n              cousin\n               \n              is\n               \n              belied\n              !"}, {"line_id": 155, "canonical_id": "ADO.4.1.155", "speaker": "BENEDICK", "text": "Lady\n              ,\n               \n              were\n               \n              you\n               \n              her\n               \n              bedfellow\n               \n              last\n               \n              night\n              ?"}, {"line_id": 156, "canonical_id": "ADO.4.1.156", "speaker": "BEATRICE", "text": "No\n              ,\n               \n              truly\n               \n              not\n              ,\n               \n              although\n               \n              until\n               \n              last\n               \n              night"}, {"line_id": 157, "canonical_id": "ADO.4.1.157", "speaker": "BEATRICE", "text": "I\n               \n              have\n               \n              this\n               \n              twelvemonth\n               \n              been\n               \n              her\n               \n              bedfellow\n              ."}, {"line_id": 158, "canonical_id": "ADO.4.1.158", "speaker": "LEONATO", "text": "Confirmed\n              ,\n               \n              confirmed\n              !\n               \n              O\n              ,\n               \n              that\n               \n              is\n               \n              stronger\n               \n              made"}, {"line_id": 159, "canonical_id": "ADO.4.1.159", "speaker": "LEONATO", "text": "Which\n               \n              was\n               \n              before\n               \n              barred\n               \n              up\n               \n              with\n               \n              ribs\n               \n              of\n               \n              iron\n              !"}, {"line_id": 160, "canonical_id": "ADO.4.1.160", "speaker": "LEONATO", "text": "Would\n               \n              the\n               \n              two\n               \n              princes\n               \n              lie\n               \n              and\n               \n              Claudio\n               \n              lie\n              ,"}, {"line_id": 161, "canonical_id": "ADO.4.1.161", "speaker": "LEONATO", "text": "Who\n               \n              loved\n               \n              her\n               \n              so\n               \n              that\n              ,\n               \n              speaking\n               \n              of\n               \n              her\n               \n              foulness\n              ,"}, {"line_id": 162, "canonical_id": "ADO.4.1.162", "speaker": "LEONATO", "text": "Washed\n               \n              it\n               \n              with\n               \n              tears\n              ?\n               \n              Hence\n               \n              from\n               \n              her\n              .\n               \n              Let\n               \n              her\n               \n              die\n              !"}, {"line_id": 163, "canonical_id": "ADO.4.1.163", "speaker": "FRIAR", "text": "Hear\n               \n              me\n               \n              a\n               \n              little\n              ,"}, {"line_id": 164, "canonical_id": "ADO.4.1.164", "speaker": "FRIAR", "text": "For\n               \n              I\n               \n              have\n               \n              only\n               \n              silent\n               \n              been\n               \n              so\n               \n              long\n              ,"}, {"line_id": 165, "canonical_id": "ADO.4.1.165", "speaker": "FRIAR", "text": "And\n               \n              given\n               \n              way\n               \n              unto\n               \n              this\n               \n              course\n               \n              of\n               \n              fortune\n              ,"}, {"line_id": 166, "canonical_id": "ADO.4.1.166", "speaker": "FRIAR", "text": "By\n               \n              noting\n               \n              of\n               \n              the\n               \n              lady\n              .\n               \n              I\n               \n              have\n               \n              marked"}, {"line_id": 167, "canonical_id": "ADO.4.1.167", "speaker": "FRIAR", "text": "A\n               \n              thousand\n               \n              blushing\n               \n              apparitions"}, {"line_id": 168, "canonical_id": "ADO.4.1.168", "speaker": "FRIAR", "text": "To\n               \n              start\n               \n              into\n               \n              her\n               \n              face\n              ,\n               \n              a\n               \n              thousand\n               \n              innocent\n               \n              shames"}, {"line_id": 169, "canonical_id": "ADO.4.1.169", "speaker": "FRIAR", "text": "In\n               \n              angel\n               \n              whiteness\n               \n              beat\n               \n              away\n               \n              those\n               \n              blushes\n              ,"}, {"line_id": 170, "canonical_id": "ADO.4.1.170", "speaker": "FRIAR", "text": "And\n               \n              in\n               \n              her\n               \n              eye\n               \n              there\n               \n              hath\n               \n              appeared\n               \n              a\n               \n              fire"}, {"line_id": 171, "canonical_id": "ADO.4.1.171", "speaker": "FRIAR", "text": "To\n               \n              burn\n               \n              the\n               \n              errors\n               \n              that\n               \n              these\n               \n              princes\n               \n              hold"}, {"line_id": 172, "canonical_id": "ADO.4.1.172", "speaker": "FRIAR", "text": "Against\n               \n              her\n               \n              maiden\n               \n              truth\n              .\n               \n              Call\n               \n              me\n               \n              a\n               \n              fool\n              ,"}, {"line_id": 173, "canonical_id": "ADO.4.1.173", "speaker": "FRIAR", "text": "Trust\n               \n              not\n               \n              my\n               \n              reading\n               \n              nor\n               \n              my\n               \n              observations\n              ,"}, {"line_id": 174, "canonical_id": "ADO.4.1.174", "speaker": "FRIAR", "text": "Which\n               \n              with\n               \n              experimental\n               \n              seal\n               \n              doth\n               \n              warrant"}, {"line_id": 175, "canonical_id": "ADO.4.1.175", "speaker": "FRIAR", "text": "The\n               \n              tenor\n               \n              of\n               \n              my\n               \n              book\n              ;\n               \n              trust\n               \n              not\n               \n              my\n               \n              age\n              ,"}, {"line_id": 176, "canonical_id": "ADO.4.1.176", "speaker": "FRIAR", "text": "My\n               \n              reverence\n              ,\n               \n              calling\n              ,\n               \n              nor\n               \n              divinity\n              ,"}, {"line_id": 177, "canonical_id": "ADO.4.1.177", "speaker": "FRIAR", "text": "If\n               \n              this\n               \n              sweet\n               \n              lady\n               \n              lie\n               \n              not\n               \n              guiltless\n               \n              here"}, {"line_id": 178, "canonical_id": "ADO.4.1.178", "speaker": "FRIAR", "text": "Under\n               \n              some\n               \n              biting\n               \n              error\n              ."}, {"line_id": 179, "canonical_id": "ADO.4.1.179", "speaker": "LEONATO", "text": "Friar\n              ,\n               \n              it\n               \n              cannot\n               \n              be\n              ."}, {"line_id": 180, "canonical_id": "ADO.4.1.180", "speaker": "LEONATO", "text": "Thou\n               \n              seest\n               \n              that\n               \n              all\n               \n              the\n               \n              grace\n               \n              that\n               \n              she\n               \n              hath\n               \n              left"}, {"line_id": 181, "canonical_id": "ADO.4.1.181", "speaker": "LEONATO", "text": "Is\n               \n              that\n               \n              she\n               \n              will\n               \n              not\n               \n              add\n               \n              to\n               \n              her\n               \n              damnation"}, {"line_id": 182, "canonical_id": "ADO.4.1.182", "speaker": "LEONATO", "text": "A\n               \n              sin\n               \n              of\n               \n              perjury\n              .\n               \n              She\n               \n              not\n               \n              denies\n               \n              it\n              ."}, {"line_id": 183, "canonical_id": "ADO.4.1.183", "speaker": "LEONATO", "text": "Why\n               \n              seek’st\n               \n              thou\n               \n              then\n               \n              to\n               \n              cover\n               \n              with\n               \n              excuse"}, {"line_id": 184, "canonical_id": "ADO.4.1.184", "speaker": "LEONATO", "text": "That\n               \n              which\n               \n              appears\n               \n              in\n               \n              proper\n               \n              nakedness\n              ?"}, {"line_id": 185, "canonical_id": "ADO.4.1.185", "speaker": "FRIAR", "text": "Lady\n              ,\n               \n              what\n               \n              man\n               \n              is\n               \n              he\n               \n              you\n               \n              are\n               \n              accused\n               \n              of\n              ?"}, {"line_id": 186, "canonical_id": "ADO.4.1.186", "speaker": "HERO", "text": "They\n               \n              know\n               \n              that\n               \n              do\n               \n              accuse\n               \n              me\n              .\n               \n              I\n               \n              know\n               \n              none\n              ."}, {"line_id": 187, "canonical_id": "ADO.4.1.187", "speaker": "HERO", "text": "If\n               \n              I\n               \n              know\n               \n              more\n               \n              of\n               \n              any\n               \n              man\n               \n              alive"}, {"line_id": 188, "canonical_id": "ADO.4.1.188", "speaker": "HERO", "text": "Than\n               \n              that\n               \n              which\n               \n              maiden\n               \n              modesty\n               \n              doth\n               \n              warrant\n              ,"}, {"line_id": 189, "canonical_id": "ADO.4.1.189", "speaker": "HERO", "text": "Let\n               \n              all\n               \n              my\n               \n              sins\n               \n              lack\n               \n              mercy\n              !\n              —\n              O\n               \n              my\n               \n              father\n              ,"}, {"line_id": 190, "canonical_id": "ADO.4.1.190", "speaker": "HERO", "text": "Prove\n               \n              you\n               \n              that\n               \n              any\n               \n              man\n               \n              with\n               \n              me\n               \n              conversed"}, {"line_id": 191, "canonical_id": "ADO.4.1.191", "speaker": "HERO", "text": "At\n               \n              hours\n               \n              unmeet\n              ,\n               \n              or\n               \n              that\n               \n              I\n               \n              yesternight"}, {"line_id": 192, "canonical_id": "ADO.4.1.192", "speaker": "HERO", "text": "Maintained\n               \n              the\n               \n              change\n               \n              of\n               \n              words\n               \n              with\n               \n              any\n               \n              creature\n              ,"}, {"line_id": 193, "canonical_id": "ADO.4.1.193", "speaker": "HERO", "text": "Refuse\n               \n              me\n              ,\n               \n              hate\n               \n              me\n              ,\n               \n              torture\n               \n              me\n               \n              to\n               \n              death\n              !"}, {"line_id": 194, "canonical_id": "ADO.4.1.194", "speaker": "FRIAR", "text": "There\n               \n              is\n               \n              some\n               \n              strange\n               \n              misprision\n               \n              in\n               \n              the\n               \n              princes\n              ."}, {"line_id": 195, "canonical_id": "ADO.4.1.195", "speaker": "BENEDICK", "text": "Two\n               \n              of\n               \n              them\n               \n              have\n               \n              the\n               \n              very\n               \n              bent\n               \n              of\n               \n              honor\n              ,"}, {"line_id": 196, "canonical_id": "ADO.4.1.196", "speaker": "BENEDICK", "text": "And\n               \n              if\n               \n              their\n               \n              wisdoms\n               \n              be\n               \n              misled\n               \n              in\n               \n              this\n              ,"}, {"line_id": 197, "canonical_id": "ADO.4.1.197", "speaker": "BENEDICK", "text": "The\n               \n              practice\n               \n              of\n               \n              it\n               \n              lives\n               \n              in\n               \n              John\n               \n              the\n               \n              Bastard\n              ,"}, {"line_id": 198, "canonical_id": "ADO.4.1.198", "speaker": "BENEDICK", "text": "Whose\n               \n              spirits\n               \n              toil\n               \n              in\n               \n              frame\n               \n              of\n               \n              villainies\n              ."}, {"line_id": 199, "canonical_id": "ADO.4.1.199", "speaker": "LEONATO", "text": "I\n               \n              know\n               \n              not\n              .\n               \n              If\n               \n              they\n               \n              speak\n               \n              but\n               \n              truth\n               \n              of\n               \n              her\n              ,"}, {"line_id": 200, "canonical_id": "ADO.4.1.200", "speaker": "LEONATO", "text": "These\n               \n              hands\n               \n              shall\n               \n              tear\n               \n              her\n              .\n               \n              If\n               \n              they\n               \n              wrong\n               \n              her\n               \n              honor\n              ,"}, {"line_id": 201, "canonical_id": "ADO.4.1.201", "speaker": "LEONATO", "text": "The\n               \n              proudest\n               \n              of\n               \n              them\n               \n              shall\n               \n              well\n               \n              hear\n               \n              of\n               \n              it\n              ."}, {"line_id": 202, "canonical_id": "ADO.4.1.202", "speaker": "LEONATO", "text": "Time\n               \n              hath\n               \n              not\n               \n              yet\n               \n              so\n               \n              dried\n               \n              this\n               \n              blood\n               \n              of\n               \n              mine\n              ,"}, {"line_id": 203, "canonical_id": "ADO.4.1.203", "speaker": "LEONATO", "text": "Nor\n               \n              age\n               \n              so\n               \n              eat\n               \n              up\n               \n              my\n               \n              invention\n              ,"}, {"line_id": 204, "canonical_id": "ADO.4.1.204", "speaker": "LEONATO", "text": "Nor\n               \n              fortune\n               \n              made\n               \n              such\n               \n              havoc\n               \n              of\n               \n              my\n               \n              means\n              ,"}, {"line_id": 205, "canonical_id": "ADO.4.1.205", "speaker": "LEONATO", "text": "Nor\n               \n              my\n               \n              bad\n               \n              life\n               \n              reft\n               \n              me\n               \n              so\n               \n              much\n               \n              of\n               \n              friends\n              ,"}, {"line_id": 206, "canonical_id": "ADO.4.1.206", "speaker": "LEONATO", "text": "But\n               \n              they\n               \n              shall\n               \n              find\n              ,\n               \n              awaked\n               \n              in\n               \n              such\n               \n              a\n               \n              kind\n              ,"}, {"line_id": 207, "canonical_id": "ADO.4.1.207", "speaker": "LEONATO", "text": "Both\n               \n              strength\n               \n              of\n               \n              limb\n               \n              and\n               \n              policy\n               \n              of\n               \n              mind\n              ,"}, {"line_id": 208, "canonical_id": "ADO.4.1.208", "speaker": "LEONATO", "text": "Ability\n               \n              in\n               \n              means\n               \n              and\n               \n              choice\n               \n              of\n               \n              friends\n              ,"}, {"line_id": 209, "canonical_id": "ADO.4.1.209", "speaker": "LEONATO", "text": "To\n               \n              quit\n               \n              me\n               \n              of\n               \n              them\n               \n              throughly\n              ."}, {"line_id": 210, "canonical_id": "ADO.4.1.210", "speaker": "FRIAR", "text": "Pause\n               \n              awhile\n              ,"}, {"line_id": 211, "canonical_id": "ADO.4.1.211", "speaker": "FRIAR", "text": "And\n               \n              let\n               \n              my\n               \n              counsel\n               \n              sway\n               \n              you\n               \n              in\n               \n              this\n               \n              case\n              ."}, {"line_id": 212, "canonical_id": "ADO.4.1.212", "speaker": "FRIAR", "text": "Your\n               \n              daughter\n               \n              here\n               \n              the\n               \n              princes\n               \n              left\n               \n              for\n               \n              dead\n              ."}, {"line_id": 213, "canonical_id": "ADO.4.1.213", "speaker": "FRIAR", "text": "Let\n               \n              her\n               \n              awhile\n               \n              be\n               \n              secretly\n               \n              kept\n               \n              in\n              ,"}, {"line_id": 214, "canonical_id": "ADO.4.1.214", "speaker": "FRIAR", "text": "And\n               \n              publish\n               \n              it\n               \n              that\n               \n              she\n               \n              is\n               \n              dead\n               \n              indeed\n              ."}, {"line_id": 215, "canonical_id": "ADO.4.1.215", "speaker": "FRIAR", "text": "Maintain\n               \n              a\n               \n              mourning\n               \n              ostentation\n              ,"}, {"line_id": 216, "canonical_id": "ADO.4.1.216", "speaker": "FRIAR", "text": "And\n               \n              on\n               \n              your\n               \n              family’s\n               \n              old\n               \n              monument"}, {"line_id": 217, "canonical_id": "ADO.4.1.217", "speaker": "FRIAR", "text": "Hang\n               \n              mournful\n               \n              epitaphs\n               \n              and\n               \n              do\n               \n              all\n               \n              rites"}, {"line_id": 218, "canonical_id": "ADO.4.1.218", "speaker": "FRIAR", "text": "That\n               \n              appertain\n               \n              unto\n               \n              a\n               \n              burial\n              ."}, {"line_id": 219, "canonical_id": "ADO.4.1.219", "speaker": "LEONATO", "text": "What\n               \n              shall\n               \n              become\n               \n              of\n               \n              this\n              ?\n               \n              What\n               \n              will\n               \n              this\n               \n              do\n              ?"}, {"line_id": 220, "canonical_id": "ADO.4.1.220", "speaker": "FRIAR", "text": "Marry\n              ,\n               \n              this\n               \n              well\n               \n              carried\n               \n              shall\n               \n              on\n               \n              her\n               \n              behalf"}, {"line_id": 221, "canonical_id": "ADO.4.1.221", "speaker": "FRIAR", "text": "Change\n               \n              slander\n               \n              to\n               \n              remorse\n              .\n               \n              That\n               \n              is\n               \n              some\n               \n              good\n              ."}, {"line_id": 222, "canonical_id": "ADO.4.1.222", "speaker": "FRIAR", "text": "But\n               \n              not\n               \n              for\n               \n              that\n               \n              dream\n               \n              I\n               \n              on\n               \n              this\n               \n              strange\n               \n              course\n              ,"}, {"line_id": 223, "canonical_id": "ADO.4.1.223", "speaker": "FRIAR", "text": "But\n               \n              on\n               \n              this\n               \n              travail\n               \n              look\n               \n              for\n               \n              greater\n               \n              birth\n              ."}, {"line_id": 224, "canonical_id": "ADO.4.1.224", "speaker": "FRIAR", "text": "She\n              ,\n               \n              dying\n              ,\n               \n              as\n               \n              it\n               \n              must\n               \n              be\n               \n              so\n               \n              maintained\n              ,"}, {"line_id": 225, "canonical_id": "ADO.4.1.225", "speaker": "FRIAR", "text": "Upon\n               \n              the\n               \n              instant\n               \n              that\n               \n              she\n               \n              was\n               \n              accused\n              ,"}, {"line_id": 226, "canonical_id": "ADO.4.1.226", "speaker": "FRIAR", "text": "Shall\n               \n              be\n               \n              lamented\n              ,\n               \n              pitied\n              ,\n               \n              and\n               \n              excused"}, {"line_id": 227, "canonical_id": "ADO.4.1.227", "speaker": "FRIAR", "text": "Of\n               \n              every\n               \n              hearer\n              .\n               \n              For\n               \n              it\n               \n              so\n               \n              falls\n               \n              out"}, {"line_id": 228, "canonical_id": "ADO.4.1.228", "speaker": "FRIAR", "text": "That\n               \n              what\n               \n              we\n               \n              have\n               \n              we\n               \n              prize\n               \n              not\n               \n              to\n               \n              the\n               \n              worth"}, {"line_id": 229, "canonical_id": "ADO.4.1.229", "speaker": "FRIAR", "text": "Whiles\n               \n              we\n               \n              enjoy\n               \n              it\n              ,\n               \n              but\n               \n              being\n               \n              lacked\n               \n              and\n               \n              lost\n              ,"}, {"line_id": 230, "canonical_id": "ADO.4.1.230", "speaker": "FRIAR", "text": "Why\n               \n              then\n               \n              we\n               \n              rack\n               \n              the\n               \n              value\n              ,\n               \n              then\n               \n              we\n               \n              find"}, {"line_id": 231, "canonical_id": "ADO.4.1.231", "speaker": "FRIAR", "text": "The\n               \n              virtue\n               \n              that\n               \n              possession\n               \n              would\n               \n              not\n               \n              show\n               \n              us"}, {"line_id": 232, "canonical_id": "ADO.4.1.232", "speaker": "FRIAR", "text": "Whiles\n               \n              it\n               \n              was\n               \n              ours\n              .\n               \n              So\n               \n              will\n               \n              it\n               \n              fare\n               \n              with\n               \n              Claudio\n              ."}, {"line_id": 233, "canonical_id": "ADO.4.1.233", "speaker": "FRIAR", "text": "When\n               \n              he\n               \n              shall\n               \n              hear\n               \n              she\n               \n              died\n               \n              upon\n               \n              his\n               \n              words\n              ,"}, {"line_id": 234, "canonical_id": "ADO.4.1.234", "speaker": "FRIAR", "text": "Th’\n               \n              idea\n               \n              of\n               \n              her\n               \n              life\n               \n              shall\n               \n              sweetly\n               \n              creep"}, {"line_id": 235, "canonical_id": "ADO.4.1.235", "speaker": "FRIAR", "text": "Into\n               \n              his\n               \n              study\n               \n              of\n               \n              imagination\n              ,"}, {"line_id": 236, "canonical_id": "ADO.4.1.236", "speaker": "FRIAR", "text": "And\n               \n              every\n               \n              lovely\n               \n              organ\n               \n              of\n               \n              her\n               \n              life"}, {"line_id": 237, "canonical_id": "ADO.4.1.237", "speaker": "FRIAR", "text": "Shall\n               \n              come\n               \n              appareled\n               \n              in\n               \n              more\n               \n              precious\n               \n              habit\n              ,"}, {"line_id": 238, "canonical_id": "ADO.4.1.238", "speaker": "FRIAR", "text": "More\n               \n              moving\n              ,\n               \n              delicate\n              ,\n               \n              and\n               \n              full\n               \n              of\n               \n              life\n              ,"}, {"line_id": 239, "canonical_id": "ADO.4.1.239", "speaker": "FRIAR", "text": "Into\n               \n              the\n               \n              eye\n               \n              and\n               \n              prospect\n               \n              of\n               \n              his\n               \n              soul\n              ,"}, {"line_id": 240, "canonical_id": "ADO.4.1.240", "speaker": "FRIAR", "text": "Than\n               \n              when\n               \n              she\n               \n              lived\n               \n              indeed\n              .\n               \n              Then\n               \n              shall\n               \n              he\n               \n              mourn\n              ,"}, {"line_id": 241, "canonical_id": "ADO.4.1.241", "speaker": "FRIAR", "text": "If\n               \n              ever\n               \n              love\n               \n              had\n               \n              interest\n               \n              in\n               \n              his\n               \n              liver\n              ,"}, {"line_id": 242, "canonical_id": "ADO.4.1.242", "speaker": "FRIAR", "text": "And\n               \n              wish\n               \n              he\n               \n              had\n               \n              not\n               \n              so\n               \n              accused\n               \n              her\n              ,"}, {"line_id": 243, "canonical_id": "ADO.4.1.243", "speaker": "FRIAR", "text": "No\n              ,\n               \n              though\n               \n              he\n               \n              thought\n               \n              his\n               \n              accusation\n               \n              true\n              ."}, {"line_id": 244, "canonical_id": "ADO.4.1.244", "speaker": "FRIAR", "text": "Let\n               \n              this\n               \n              be\n               \n              so\n              ,\n               \n              and\n               \n              doubt\n               \n              not\n               \n              but\n               \n              success"}, {"line_id": 245, "canonical_id": "ADO.4.1.245", "speaker": "FRIAR", "text": "Will\n               \n              fashion\n               \n              the\n               \n              event\n               \n              in\n               \n              better\n               \n              shape"}, {"line_id": 246, "canonical_id": "ADO.4.1.246", "speaker": "FRIAR", "text": "Than\n               \n              I\n               \n              can\n               \n              lay\n               \n              it\n               \n              down\n               \n              in\n               \n              likelihood\n              ."}, {"line_id": 247, "canonical_id": "ADO.4.1.247", "speaker": "FRIAR", "text": "But\n               \n              if\n               \n              all\n               \n              aim\n               \n              but\n               \n              this\n               \n              be\n               \n              leveled\n               \n              false\n              ,"}, {"line_id": 248, "canonical_id": "ADO.4.1.248", "speaker": "FRIAR", "text": "The\n               \n              supposition\n               \n              of\n               \n              the\n               \n              lady’s\n               \n              death"}, {"line_id": 249, "canonical_id": "ADO.4.1.249", "speaker": "FRIAR", "text": "Will\n               \n              quench\n               \n              the\n               \n              wonder\n               \n              of\n               \n              her\n               \n              infamy\n              ."}, {"line_id": 250, "canonical_id": "ADO.4.1.250", "speaker": "FRIAR", "text": "And\n               \n              if\n               \n              it\n               \n              sort\n               \n              not\n               \n              well\n              ,\n               \n              you\n               \n              may\n               \n              conceal\n               \n              her\n              ,"}, {"line_id": 251, "canonical_id": "ADO.4.1.251", "speaker": "FRIAR", "text": "As\n               \n              best\n               \n              befits\n               \n              her\n               \n              wounded\n               \n              reputation\n              ,"}, {"line_id": 252, "canonical_id": "ADO.4.1.252", "speaker": "FRIAR", "text": "In\n               \n              some\n               \n              reclusive\n               \n              and\n               \n              religious\n               \n              life\n              ,"}, {"line_id": 253, "canonical_id": "ADO.4.1.253", "speaker": "FRIAR", "text": "Out\n               \n              of\n               \n              all\n               \n              eyes\n              ,\n               \n              tongues\n              ,\n               \n              minds\n              ,\n               \n              and\n               \n              injuries\n              ."}, {"line_id": 254, "canonical_id": "ADO.4.1.254", "speaker": "BENEDICK", "text": "Signior\n               \n              Leonato\n              ,\n               \n              let\n               \n              the\n               \n              Friar\n               \n              advise\n               \n              you\n              ."}, {"line_id": 255, "canonical_id": "ADO.4.1.255", "speaker": "BENEDICK", "text": "And\n               \n              though\n               \n              you\n               \n              know\n               \n              my\n               \n              inwardness\n               \n              and\n               \n              love"}, {"line_id": 256, "canonical_id": "ADO.4.1.256", "speaker": "BENEDICK", "text": "Is\n               \n              very\n               \n              much\n               \n              unto\n               \n              the\n               \n              Prince\n               \n              and\n               \n              Claudio\n              ,"}, {"line_id": 257, "canonical_id": "ADO.4.1.257", "speaker": "BENEDICK", "text": "Yet\n              ,\n               \n              by\n               \n              mine\n               \n              honor\n              ,\n               \n              I\n               \n              will\n               \n              deal\n               \n              in\n               \n              this"}, {"line_id": 258, "canonical_id": "ADO.4.1.258", "speaker": "BENEDICK", "text": "As\n               \n              secretly\n               \n              and\n               \n              justly\n               \n              as\n               \n              your\n               \n              soul"}, {"line_id": 259, "canonical_id": "ADO.4.1.259", "speaker": "BENEDICK", "text": "Should\n               \n              with\n               \n              your\n               \n              body\n              ."}, {"line_id": 260, "canonical_id": "ADO.4.1.260", "speaker": "LEONATO", "text": "Being\n               \n              that\n               \n              I\n               \n              flow\n               \n              in\n               \n              grief\n              ,"}, {"line_id": 261, "canonical_id": "ADO.4.1.261", "speaker": "LEONATO", "text": "The\n               \n              smallest\n               \n              twine\n               \n              may\n               \n              lead\n               \n              me\n              ."}, {"line_id": 262, "canonical_id": "ADO.4.1.262", "speaker": "FRIAR", "text": "FRIAR\n            \n            \n              \n                ’Tis\n                 \n                well\n                 \n                consented\n                .\n                 \n                Presently\n                 \n                away\n                ,\n              \n              \n                For\n                 \n                to\n                 \n                strange\n                 \n                sores\n                 \n                strangely\n                 \n                they\n                 \n                strain\n                 \n                the\n                 \n                cure\n                .\n                —\n              \n              \n                Come\n                ,\n                 \n                lady\n                ,\n                 \n                die\n                 \n                to\n                 \n                live\n                .\n                 \n                This\n                 \n                wedding\n                 \n                day\n              \n              \n                Perhaps\n                 \n                is\n                 \n                but\n                 \n                prolonged\n                .\n                 \n                Have\n                 \n                patience\n                 \n                and\n                 \n                endure\n                .\n              \n              \n                All\n                 \n                but\n                 \n                Beatrice\n                 \n                and\n                 \n                Benedick\n                 \n                exit\n                ."}, {"line_id": 263, "canonical_id": "ADO.4.1.263", "speaker": "BENEDICK", "text": "Lady Beatrice, have you wept all this while?"}, {"line_id": 264, "canonical_id": "ADO.4.1.264", "speaker": "BEATRICE", "text": "Yea, and I will weep a while longer."}, {"line_id": 265, "canonical_id": "ADO.4.1.265", "speaker": "BENEDICK", "text": "I will not desire that."}, {"line_id": 266, "canonical_id": "ADO.4.1.266", "speaker": "BEATRICE", "text": "You have no reason. I do it freely."}, {"line_id": 267, "canonical_id": "ADO.4.1.267", "speaker": "BENEDICK", "text": "Surely I do believe your fair cousin is"}, {"line_id": 268, "canonical_id": "ADO.4.1.268", "speaker": "BENEDICK", "text": "wronged."}, {"line_id": 269, "canonical_id": "ADO.4.1.269", "speaker": "BEATRICE", "text": "Ah, how much might the man deserve of me"}, {"line_id": 270, "canonical_id": "ADO.4.1.270", "speaker": "BEATRICE", "text": "that would right her!"}, {"line_id": 271, "canonical_id": "ADO.4.1.271", "speaker": "BENEDICK", "text": "Is there any way to show such friendship?"}, {"line_id": 272, "canonical_id": "ADO.4.1.272", "speaker": "BEATRICE", "text": "A very even way, but no such friend."}, {"line_id": 273, "canonical_id": "ADO.4.1.273", "speaker": "BENEDICK", "text": "May a man do it?"}, {"line_id": 274, "canonical_id": "ADO.4.1.274", "speaker": "BEATRICE", "text": "It is a man’s office, but not yours."}, {"line_id": 275, "canonical_id": "ADO.4.1.275", "speaker": "BENEDICK", "text": "I do love nothing in the world so well as"}, {"line_id": 276, "canonical_id": "ADO.4.1.276", "speaker": "BENEDICK", "text": "you. Is not that strange?"}, {"line_id": 277, "canonical_id": "ADO.4.1.277", "speaker": "BEATRICE", "text": "As strange as the thing I know not. It were as"}, {"line_id": 278, "canonical_id": "ADO.4.1.278", "speaker": "BEATRICE", "text": "possible for me to say I loved nothing so well as you,"}, {"line_id": 279, "canonical_id": "ADO.4.1.279", "speaker": "BEATRICE", "text": "but believe me not, and yet I lie not; I confess"}, {"line_id": 280, "canonical_id": "ADO.4.1.280", "speaker": "BEATRICE", "text": "nothing, nor I deny nothing. I am sorry for my"}, {"line_id": 281, "canonical_id": "ADO.4.1.281", "speaker": "BEATRICE", "text": "cousin."}, {"line_id": 282, "canonical_id": "ADO.4.1.282", "speaker": "BENEDICK", "text": "By my sword, Beatrice, thou lovest me!"}, {"line_id": 283, "canonical_id": "ADO.4.1.283", "speaker": "BEATRICE", "text": "Do not swear and eat it."}, {"line_id": 284, "canonical_id": "ADO.4.1.284", "speaker": "BENEDICK", "text": "I will swear by it that you love me, and I will"}, {"line_id": 285, "canonical_id": "ADO.4.1.285", "speaker": "BENEDICK", "text": "make him eat it that says I love not you."}, {"line_id": 286, "canonical_id": "ADO.4.1.286", "speaker": "BEATRICE", "text": "Will you not eat your word?"}, {"line_id": 287, "canonical_id": "ADO.4.1.287", "speaker": "BENEDICK", "text": "With no sauce that can be devised to it. I"}, {"line_id": 288, "canonical_id": "ADO.4.1.288", "speaker": "BENEDICK", "text": "protest I love thee."}, {"line_id": 289, "canonical_id": "ADO.4.1.289", "speaker": "BEATRICE", "text": "Why then, God forgive me."}, {"line_id": 290, "canonical_id": "ADO.4.1.290", "speaker": "BENEDICK", "text": "What offense, sweet Beatrice?"}, {"line_id": 291, "canonical_id": "ADO.4.1.291", "speaker": "BEATRICE", "text": "You have stayed me in a happy hour. I was"}, {"line_id": 292, "canonical_id": "ADO.4.1.292", "speaker": "BEATRICE", "text": "about to protest I loved you."}, {"line_id": 293, "canonical_id": "ADO.4.1.293", "speaker": "BENEDICK", "text": "And do it with all thy heart."}, {"line_id": 294, "canonical_id": "ADO.4.1.294", "speaker": "BEATRICE", "text": "I love you with so much of my heart that"}, {"line_id": 295, "canonical_id": "ADO.4.1.295", "speaker": "BEATRICE", "text": "none is left to protest."}, {"line_id": 296, "canonical_id": "ADO.4.1.296", "speaker": "BENEDICK", "text": "Come, bid me do anything for thee."}, {"line_id": 297, "canonical_id": "ADO.4.1.297", "speaker": "BEATRICE", "text": "Kill Claudio."}, {"line_id": 298, "canonical_id": "ADO.4.1.298", "speaker": "BENEDICK", "text": "Ha! Not for the wide world."}, {"line_id": 299, "canonical_id": "ADO.4.1.299", "speaker": "BEATRICE", "text": "You kill me to deny it. Farewell."}, {"line_id": 300, "canonical_id": "ADO.4.1.300", "speaker": "BENEDICK", "text": "Tarry, sweet Beatrice."}, {"line_id": 301, "canonical_id": "ADO.4.1.301", "speaker": "BEATRICE", "text": "I am gone, though I am here. There is no"}, {"line_id": 302, "canonical_id": "ADO.4.1.302", "speaker": "BEATRICE", "text": "love in you. Nay, I pray you let me go."}, {"line_id": 303, "canonical_id": "ADO.4.1.303", "speaker": "BENEDICK", "text": "Beatrice—"}, {"line_id": 304, "canonical_id": "ADO.4.1.304", "speaker": "BEATRICE", "text": "In faith, I will go."}, {"line_id": 305, "canonical_id": "ADO.4.1.305", "speaker": "BENEDICK", "text": "We’ll be friends first."}, {"line_id": 306, "canonical_id": "ADO.4.1.306", "speaker": "BEATRICE", "text": "You dare easier be friends with me than"}, {"line_id": 307, "canonical_id": "ADO.4.1.307", "speaker": "BEATRICE", "text": "fight with mine enemy."}, {"line_id": 308, "canonical_id": "ADO.4.1.308", "speaker": "BENEDICK", "text": "Is Claudio thine enemy?"}, {"line_id": 309, "canonical_id": "ADO.4.1.309", "speaker": "BEATRICE", "text": "Is he not approved in the height a villain"}, {"line_id": 310, "canonical_id": "ADO.4.1.310", "speaker": "BEATRICE", "text": "that hath slandered, scorned, dishonored my kinswoman?"}, {"line_id": 311, "canonical_id": "ADO.4.1.311", "speaker": "BEATRICE", "text": "O, that I were a man! What, bear her in"}, {"line_id": 312, "canonical_id": "ADO.4.1.312", "speaker": "BEATRICE", "text": "hand until they come to take hands, and then, with"}, {"line_id": 313, "canonical_id": "ADO.4.1.313", "speaker": "BEATRICE", "text": "public accusation, uncovered slander, unmitigated"}, {"line_id": 314, "canonical_id": "ADO.4.1.314", "speaker": "BEATRICE", "text": "rancor—O God, that I were a man! I would eat his"}, {"line_id": 315, "canonical_id": "ADO.4.1.315", "speaker": "BEATRICE", "text": "heart in the marketplace."}, {"line_id": 316, "canonical_id": "ADO.4.1.316", "speaker": "BENEDICK", "text": "Hear me, Beatrice—"}, {"line_id": 317, "canonical_id": "ADO.4.1.317", "speaker": "BEATRICE", "text": "Talk with a man out at a window! A proper"}, {"line_id": 318, "canonical_id": "ADO.4.1.318", "speaker": "BEATRICE", "text": "saying."}, {"line_id": 319, "canonical_id": "ADO.4.1.319", "speaker": "BENEDICK", "text": "Nay, but Beatrice—"}, {"line_id": 320, "canonical_id": "ADO.4.1.320", "speaker": "BEATRICE", "text": "Sweet Hero, she is wronged, she is slandered,"}, {"line_id": 321, "canonical_id": "ADO.4.1.321", "speaker": "BEATRICE", "text": "she is undone."}, {"line_id": 322, "canonical_id": "ADO.4.1.322", "speaker": "BENEDICK", "text": "Beat—"}, {"line_id": 323, "canonical_id": "ADO.4.1.323", "speaker": "BEATRICE", "text": "Princes and counties! Surely a princely testimony,"}, {"line_id": 324, "canonical_id": "ADO.4.1.324", "speaker": "BEATRICE", "text": "a goodly count, Count Comfect, a sweet"}, {"line_id": 325, "canonical_id": "ADO.4.1.325", "speaker": "BEATRICE", "text": "gallant, surely! O, that I were a man for his sake! Or"}, {"line_id": 326, "canonical_id": "ADO.4.1.326", "speaker": "BEATRICE", "text": "that I had any friend would be a man for my sake!"}, {"line_id": 327, "canonical_id": "ADO.4.1.327", "speaker": "BEATRICE", "text": "But manhood is melted into curtsies, valor into"}, {"line_id": 328, "canonical_id": "ADO.4.1.328", "speaker": "BEATRICE", "text": "compliment, and men are only turned into tongue,"}, {"line_id": 329, "canonical_id": "ADO.4.1.329", "speaker": "BEATRICE", "text": "and trim ones, too. He is now as valiant as Hercules"}, {"line_id": 330, "canonical_id": "ADO.4.1.330", "speaker": "BEATRICE", "text": "that only tells a lie and swears it. I cannot be a man"}, {"line_id": 331, "canonical_id": "ADO.4.1.331", "speaker": "BEATRICE", "text": "with wishing; therefore I will die a woman with"}, {"line_id": 332, "canonical_id": "ADO.4.1.332", "speaker": "BEATRICE", "text": "grieving."}, {"line_id": 333, "canonical_id": "ADO.4.1.333", "speaker": "BENEDICK", "text": "Tarry, good Beatrice. By this hand, I love"}, {"line_id": 334, "canonical_id": "ADO.4.1.334", "speaker": "BENEDICK", "text": "thee."}, {"line_id": 335, "canonical_id": "ADO.4.1.335", "speaker": "BEATRICE", "text": "Use it for my love some other way than"}, {"line_id": 336, "canonical_id": "ADO.4.1.336", "speaker": "BEATRICE", "text": "swearing by it."}, {"line_id": 337, "canonical_id": "ADO.4.1.337", "speaker": "BENEDICK", "text": "Think you in your soul the Count Claudio"}, {"line_id": 338, "canonical_id": "ADO.4.1.338", "speaker": "BENEDICK", "text": "hath wronged Hero?"}, {"line_id": 339, "canonical_id": "ADO.4.1.339", "speaker": "BEATRICE", "text": "Yea, as sure as I have a thought or a soul."}, {"line_id": 340, "canonical_id": "ADO.4.1.340", "speaker": "BENEDICK", "text": "Enough, I am engaged. I will challenge"}, {"line_id": 341, "canonical_id": "ADO.4.1.341", "speaker": "BENEDICK", "text": "him. I will kiss your hand, and so I leave you. By"}, {"line_id": 342, "canonical_id": "ADO.4.1.342", "speaker": "BENEDICK", "text": "this hand, Claudio shall render me a dear account."}, {"line_id": 343, "canonical_id": "ADO.4.1.343", "speaker": "BENEDICK", "text": "As you hear of me, so think of me. Go comfort your"}, {"line_id": 344, "canonical_id": "ADO.4.1.344", "speaker": "BENEDICK", "text": "cousin. I must say she is dead, and so farewell."}]